Workbook

Sheet README
A1: InventoryIQ - Inventory Forecasting & Replenishment Workbook
A2: Data source: SYNTHETIC demo data - not Walmart data. Planning date: 2026-04-27.
A4: Purpose | B4: Working analyst view of the InventoryIQ planning engine: demand forecasts, safety stock, reorder points, and purchase recommendations.
A5: How to use | B5: Change the yellow cells on the Assumptions sheet. Safety Stock, Reorder Points, Inventory Summary and Purchase Recs recalculate with live formulas.
A6: Not recalculated in Excel | B6: Forecasts, budget/capacity allocation and the historical simulation are produced by the Python engine and pasted as values (labelled 'Python').
A7: Lineage: OBSERVED | B7: Recorded M5 sales, prices and calendar.
A8: Lineage: DERIVED | B8: Statistics calculated directly from observed data (ABC/XYZ, demand pattern, list price).
A9: Lineage: MODELED | B9: Forecasts, forecast error, safety stock, reorder points, recommendations.
A10: Lineage: SIMULATED | B10: Suppliers, lead times, MOQs, case packs, unit costs, stock on hand, purchase orders and all financial results. These are assumptions, not Walmart operations.
A11: Refresh | B11: python -m inventoryiq.pipeline --source m5 (full run) or python -m inventoryiq.excel_workbook --source m5 (workbook only).
A12: Validation | B12: python -m inventoryiq.excel_workbook --source m5 --validate recalculates every formula and compares it with the Python reference engine.
A13: Sheets | B13: Assumptions | Inventory Summary | ABC_XYZ | Forecasts | Safety Stock | Reorder Points | Purchase Recs | Suppliers | Scenarios | Data Definitions

Sheet Assumptions
A1: Planning assumptions
A2: Yellow cells are inputs. Defaults match the application's Balanced scenario.
A4: Parameter | B4: Unit | C4: Value | D4: Lineage | E4: Notes
A5: Target cycle service level | B5: probability | C5: 0.95 | D5: Assumed | E5: Probability of no stockout per replenishment cycle (not the fill rate).
A6: Review interval R | B6: days | C6: 7 | D6: Assumed | E6: Days between purchasing reviews.
A7: Lead-time shift | B7: days | C7: 0 | D7: Assumed | E7: Added to every supplier's mean lead time (min 1 day).
A8: Lead-time variability multiplier | B8: x | C8: 1 | D8: Assumed | E8: Multiplies each supplier's lead-time standard deviation.
A9: Annual holding cost rate | B9: % of cost | C9: 0.25 | D9: Simulated | E9: Capital, storage and obsolescence per unit-year.
A10: Shortage penalty multiplier | B10: x margin | C10: 1.5 | D10: Simulated | E10: Penalty per lost unit = multiplier x unit gross margin.
A11: Maximum days of supply per order | B11: days | C11: 28 | D11: Assumed | E11: Policy v2 lot-size cap: cycle stock <= mu x this many days.
A12: z = NORMSINV(service level) | B12: std. normal | C12: =NORMSINV(Assumptions!$C$5) | E12: Normal quantile used in the safety-stock formula.
A14: Settings equal defaults? | C14: =IF(AND(Assumptions!$C$5=0.95,Assumptions!$C$6=7,Assumptions!$C$7=0.0,Assumptions!$C$8=1.0,Assumptions!$C$11=28.0),"YES","NO") | E14: Empirical fallback reorder points and Python check columns are valid only when this reads YES.
A16: Safety stock formula | E16: SS = z x SQRT(P x sigma_d^2 + mu_d^2 x Var[L]), P = E[L] + R (periodic-review protection period)
A17: Reorder point | E17: s = mu_d x P + SS; for intermittent/lumpy items s = max(s, empirical CSL-quantile of P-day demand)
A18: Order-up-to level | E18: S = s + min(max(EOQ, mu_d x R), mu_d x max days); EOQ = SQRT(2 x 365 x mu_d x order cost / (holding rate x unit cost))
A19: Order quantity | E19: If IP <= s: Q = max(CEILING((S - IP) / case) x case, MOQ); IP = on hand + on order (lost-sales model, no backorders)

Sheet Inventory Summary
A1: Inventory summary (SIMULATED stock, MODELED risk)
A2: Simulated on-hand stock at the planning date valued at simulated unit cost.
A4: Series | B4: Item | C4: Store | D4: Category | E4: Supplier | F4: On hand | G4: On order | H4: Unit cost | I4: Inventory value | J4: Coverage (days) | K4: Risk | L4: P(stockout before receipt) | N4: Summary
A5: SYN_FOODS_1_001_CA_1 | B5: SYN_FOODS_1_001 | C5: CA_1 | D5: FOODS | E5: SUP-01 | F5: 75 | G5: 0 | H5: 3.77 | I5: =F5*H5 | J5: ='Reorder Points'!T5 | K5: Medium | L5: 1.7640294e-08 | N5: Inventory value | O5: CA_1 | P5: CA_2
A6: SYN_FOODS_1_003_CA_1 | B6: SYN_FOODS_1_003 | C6: CA_1 | D6: FOODS | E6: SUP-01 | F6: 28 | G6: 0 | H6: 1.88 | I6: =F6*H6 | J6: ='Reorder Points'!T6 | K6: Low | L6: 0 | N6: FOODS | O6: =SUMIFS($I$5:$I$84,$D$5:$D$84,$N6,$C$5:$C$84,O$5) | P6: =SUMIFS($I$5:$I$84,$D$5:$D$84,$N6,$C$5:$C$84,P$5)
A7: SYN_FOODS_1_008_CA_1 | B7: SYN_FOODS_1_008 | C7: CA_1 | D7: FOODS | E7: SUP-01 | F7: 30 | G7: 0 | H7: 4.63 | I7: =F7*H7 | J7: ='Reorder Points'!T7 | K7: Medium | L7: 0.0018553548 | N7: HOBBIES | O7: =SUMIFS($I$5:$I$84,$D$5:$D$84,$N7,$C$5:$C$84,O$5) | P7: =SUMIFS($I$5:$I$84,$D$5:$D$84,$N7,$C$5:$C$84,P$5)
A8: SYN_FOODS_1_009_CA_1 | B8: SYN_FOODS_1_009 | C8: CA_1 | D8: FOODS | E8: SUP-01 | F8: 318 | G8: 0 | H8: 5.45 | I8: =F8*H8 | J8: ='Reorder Points'!T8 | K8: Low | L8: 0 | N8: HOUSEHOLD | O8: =SUMIFS($I$5:$I$84,$D$5:$D$84,$N8,$C$5:$C$84,O$5) | P8: =SUMIFS($I$5:$I$84,$D$5:$D$84,$N8,$C$5:$C$84,P$5)
A9: SYN_FOODS_2_004_CA_1 | B9: SYN_FOODS_2_004 | C9: CA_1 | D9: FOODS | E9: SUP-02 | F9: 15 | G9: 0 | H9: 2.01 | I9: =F9*H9 | J9: ='Reorder Points'!T9 | K9: Medium | L9: 0.0034799799
A10: SYN_FOODS_2_005_CA_1 | B10: SYN_FOODS_2_005 | C10: CA_1 | D10: FOODS | E10: SUP-02 | F10: 12 | G10: 0 | H10: 5.21 | I10: =F10*H10 | J10: ='Reorder Points'!T10 | K10: Medium | L10: 0.34336828 | N10: Lines by risk
A11: SYN_FOODS_2_006_CA_1 | B11: SYN_FOODS_2_006 | C11: CA_1 | D11: FOODS | E11: SUP-02 | F11: 66 | G11: 0 | H11: 1.46 | I11: =F11*H11 | J11: ='Reorder Points'!T11 | K11: Low | L11: 0 | N11: High | O11: =COUNTIFS($K$5:$K$84,$N11,$C$5:$C$84,O$5) | P11: =COUNTIFS($K$5:$K$84,$N11,$C$5:$C$84,P$5)
A12: SYN_FOODS_2_008_CA_1 | B12: SYN_FOODS_2_008 | C12: CA_1 | D12: FOODS | E12: SUP-02 | F12: 7 | G12: 0 | H12: 4.95 | I12: =F12*H12 | J12: ='Reorder Points'!T12 | K12: Medium | L12: 0.22191022 | N12: Medium | O12: =COUNTIFS($K$5:$K$84,$N12,$C$5:$C$84,O$5) | P12: =COUNTIFS($K$5:$K$84,$N12,$C$5:$C$84,P$5)
A13: SYN_FOODS_2_009_CA_1 | B13: SYN_FOODS_2_009 | C13: CA_1 | D13: FOODS | E13: SUP-02 | F13: 583 | G13: 0 | H13: 4.18 | I13: =F13*H13 | J13: ='Reorder Points'!T13 | K13: Low | L13: 0 | N13: Low | O13: =COUNTIFS($K$5:$K$84,$N13,$C$5:$C$84,O$5) | P13: =COUNTIFS($K$5:$K$84,$N13,$C$5:$C$84,P$5)
A14: SYN_FOODS_3_002_CA_1 | B14: SYN_FOODS_3_002 | C14: CA_1 | D14: FOODS | E14: SUP-03 | F14: 61 | G14: 0 | H14: 2.42 | I14: =F14*H14 | J14: ='Reorder Points'!T14 | K14: Low | L14: 0
A15: SYN_FOODS_3_003_CA_1 | B15: SYN_FOODS_3_003 | C15: CA_1 | D15: FOODS | E15: SUP-03 | F15: 284 | G15: 0 | H15: 1.27 | I15: =F15*H15 | J15: ='Reorder Points'!T15 | K15: Low | L15: 0
A16: SYN_FOODS_3_004_CA_1 | B16: SYN_FOODS_3_004 | C16: CA_1 | D16: FOODS | E16: SUP-03 | F16: 276 | G16: 0 | H16: 0.96 | I16: =F16*H16 | J16: ='Reorder Points'!T16 | K16: Low | L16: 0
A17: SYN_FOODS_3_005_CA_1 | B17: SYN_FOODS_3_005 | C17: CA_1 | D17: FOODS | E17: SUP-03 | F17: 319 | G17: 0 | H17: 1.76 | I17: =F17*H17 | J17: ='Reorder Points'!T17 | K17: Low | L17: 0
A18: SYN_FOODS_3_007_CA_1 | B18: SYN_FOODS_3_007 | C18: CA_1 | D18: FOODS | E18: SUP-03 | F18: 194 | G18: 0 | H18: 1.99 | I18: =F18*H18 | J18: ='Reorder Points'!T18 | K18: Low | L18: 0
A19: SYN_FOODS_3_008_CA_1 | B19: SYN_FOODS_3_008 | C19: CA_1 | D19: FOODS | E19: SUP-03 | F19: 8 | G19: 0 | H19: 2.92 | I19: =F19*H19 | J19: ='Reorder Points'!T19 | K19: Medium | L19: 0.00036968585
A20: SYN_FOODS_3_009_CA_1 | B20: SYN_FOODS_3_009 | C20: CA_1 | D20: FOODS | E20: SUP-03 | F20: 139 | G20: 0 | H20: 5.33 | I20: =F20*H20 | J20: ='Reorder Points'!T20 | K20: Medium | L20: 1.7799311e-07
A21: SYN_HOBBIES_1_001_CA_1 | B21: SYN_HOBBIES_1_001 | C21: CA_1 | D21: HOBBIES | E21: SUP-04 | F21: 76 | G21: 0 | H21: 5.49 | I21: =F21*H21 | J21: ='Reorder Points'!T21 | K21: Medium | L21: 0.35799014
A22: SYN_HOBBIES_1_003_CA_1 | B22: SYN_HOBBIES_1_003 | C22: CA_1 | D22: HOBBIES | E22: SUP-04 | F22: 29 | G22: 0 | H22: 10.92 | I22: =F22*H22 | J22: ='Reorder Points'!T22 | K22: Medium | L22: 0.039249532
A23: SYN_HOBBIES_1_004_CA_1 | B23: SYN_HOBBIES_1_004 | C23: CA_1 | D23: HOBBIES | E23: SUP-04 | F23: 24 | G23: 0 | H23: 6.15 | I23: =F23*H23 | J23: ='Reorder Points'!T23 | K23: Low | L23: 7.2214164e-06
A24: SYN_HOBBIES_1_005_CA_1 | B24: SYN_HOBBIES_1_005 | C24: CA_1 | D24: HOBBIES | E24: SUP-04 | F24: 16 | G24: 0 | H24: 6.44 | I24: =F24*H24 | J24: ='Reorder Points'!T24 | K24: Low | L24: 0.00012579157
A25: SYN_HOBBIES_1_006_CA_1 | B25: SYN_HOBBIES_1_006 | C25: CA_1 | D25: HOBBIES | E25: SUP-04 | F25: 21 | G25: 6 | H25: 8.2 | I25: =F25*H25 | J25: ='Reorder Points'!T25 | K25: Medium | L25: 0.061321301
... A84: SYN_HOUSEHOLD_2_008_CA_2 | B84: SYN_HOUSEHOLD_2_008 | C84: CA_2 | D84: HOUSEHOLD | E84: SUP-06 | F84: 14 | G84: 120 | H84: 2.62 | I84: =F84*H84 | J84: ='Reorder Points'!T84 | K84: Low | L84: 2.0859483e-09

Sheet ABC_XYZ
A1: ABC (value) and XYZ (variability) segmentation (DERIVED)
A2: Last 364 observed days. A <80% cumulative value, B <95%, C remainder. X CV<=0.5, Y<=1.0, Z >1.0 (weekly CV).
A4: Series | B4: Category | C4: Store | D4: Units (364d) | E4: Sales value (364d) | F4: Value share | G4: Cumulative share before item | H4: ABC | I4: Weekly CV | J4: XYZ | K4: Class | L4: Python class | N4: Lines by class
A5: SYN_HOBBIES_2_006_CA_1 | B5: HOBBIES | C5: CA_1 | D5: 10163 | E5: 135819.61 | F5: =E5/SUM($E$5:$E$84) | G5: =SUM($E$5:E5)/SUM($E$5:$E$84)-F5 | H5: =IF(E5<=0,"C",IF(G5<0.8,"A",IF(G5<0.95,"B","C"))) | I5: 0.079611171 | J5: =IF(ISNUMBER(I5),IF(I5<=0.5,"X",IF(I5<=1,"Y","Z")),"Z") | K5: =H5&J5 | L5: AX | O5: X | P5: Y | Q5: Z
A6: SYN_HOBBIES_2_009_CA_2 | B6: HOBBIES | C6: CA_2 | D6: 8677 | E6: 129957.11 | F6: =E6/SUM($E$5:$E$84) | G6: =SUM($E$5:E6)/SUM($E$5:$E$84)-F6 | H6: =IF(E6<=0,"C",IF(G6<0.8,"A",IF(G6<0.95,"B","C"))) | I6: 0.11024137 | J6: =IF(ISNUMBER(I6),IF(I6<=0.5,"X",IF(I6<=1,"Y","Z")),"Z") | K6: =H6&J6 | L6: AX | N6: A | O6: =COUNTIFS($H$5:$H$84,"A",$J$5:$J$84,"X") | P6: =COUNTIFS($H$5:$H$84,"A",$J$5:$J$84,"Y") | Q6: =COUNTIFS($H$5:$H$84,"A",$J$5:$J$84,"Z")
A7: SYN_HOUSEHOLD_2_001_CA_1 | B7: HOUSEHOLD | C7: CA_1 | D7: 8113 | E7: 127905.74 | F7: =E7/SUM($E$5:$E$84) | G7: =SUM($E$5:E7)/SUM($E$5:$E$84)-F7 | H7: =IF(E7<=0,"C",IF(G7<0.8,"A",IF(G7<0.95,"B","C"))) | I7: 0.083612487 | J7: =IF(ISNUMBER(I7),IF(I7<=0.5,"X",IF(I7<=1,"Y","Z")),"Z") | K7: =H7&J7 | L7: AX | N7: B | O7: =COUNTIFS($H$5:$H$84,"B",$J$5:$J$84,"X") | P7: =COUNTIFS($H$5:$H$84,"B",$J$5:$J$84,"Y") | Q7: =COUNTIFS($H$5:$H$84,"B",$J$5:$J$84,"Z")
A8: SYN_HOUSEHOLD_1_009_CA_1 | B8: HOUSEHOLD | C8: CA_1 | D8: 5042 | E8: 96053.291 | F8: =E8/SUM($E$5:$E$84) | G8: =SUM($E$5:E8)/SUM($E$5:$E$84)-F8 | H8: =IF(E8<=0,"C",IF(G8<0.8,"A",IF(G8<0.95,"B","C"))) | I8: 0.12878091 | J8: =IF(ISNUMBER(I8),IF(I8<=0.5,"X",IF(I8<=1,"Y","Z")),"Z") | K8: =H8&J8 | L8: AX | N8: C | O8: =COUNTIFS($H$5:$H$84,"C",$J$5:$J$84,"X") | P8: =COUNTIFS($H$5:$H$84,"C",$J$5:$J$84,"Y") | Q8: =COUNTIFS($H$5:$H$84,"C",$J$5:$J$84,"Z")
A9: SYN_HOUSEHOLD_2_004_CA_2 | B9: HOUSEHOLD | C9: CA_2 | D9: 8365 | E9: 80398.302 | F9: =E9/SUM($E$5:$E$84) | G9: =SUM($E$5:E9)/SUM($E$5:$E$84)-F9 | H9: =IF(E9<=0,"C",IF(G9<0.8,"A",IF(G9<0.95,"B","C"))) | I9: 0.099202911 | J9: =IF(ISNUMBER(I9),IF(I9<=0.5,"X",IF(I9<=1,"Y","Z")),"Z") | K9: =H9&J9 | L9: AX
A10: SYN_HOUSEHOLD_1_009_CA_2 | B10: HOUSEHOLD | C10: CA_2 | D10: 4210 | E10: 79498.011 | F10: =E10/SUM($E$5:$E$84) | G10: =SUM($E$5:E10)/SUM($E$5:$E$84)-F10 | H10: =IF(E10<=0,"C",IF(G10<0.8,"A",IF(G10<0.95,"B","C"))) | I10: 0.13365748 | J10: =IF(ISNUMBER(I10),IF(I10<=0.5,"X",IF(I10<=1,"Y","Z")),"Z") | K10: =H10&J10 | L10: AX
A11: SYN_HOUSEHOLD_2_001_CA_2 | B11: HOUSEHOLD | C11: CA_2 | D11: 4725 | E11: 73921.83 | F11: =E11/SUM($E$5:$E$84) | G11: =SUM($E$5:E11)/SUM($E$5:$E$84)-F11 | H11: =IF(E11<=0,"C",IF(G11<0.8,"A",IF(G11<0.95,"B","C"))) | I11: 0.11112724 | J11: =IF(ISNUMBER(I11),IF(I11<=0.5,"X",IF(I11<=1,"Y","Z")),"Z") | K11: =H11&J11 | L11: AX
A12: SYN_HOBBIES_2_005_CA_1 | B12: HOBBIES | C12: CA_1 | D12: 8970 | E12: 68010.702 | F12: =E12/SUM($E$5:$E$84) | G12: =SUM($E$5:E12)/SUM($E$5:$E$84)-F12 | H12: =IF(E12<=0,"C",IF(G12<0.8,"A",IF(G12<0.95,"B","C"))) | I12: 0.087853665 | J12: =IF(ISNUMBER(I12),IF(I12<=0.5,"X",IF(I12<=1,"Y","Z")),"Z") | K12: =H12&J12 | L12: AX
A13: SYN_HOUSEHOLD_2_004_CA_1 | B13: HOUSEHOLD | C13: CA_1 | D13: 6219 | E13: 60457.591 | F13: =E13/SUM($E$5:$E$84) | G13: =SUM($E$5:E13)/SUM($E$5:$E$84)-F13 | H13: =IF(E13<=0,"C",IF(G13<0.8,"A",IF(G13<0.95,"B","C"))) | I13: 0.11522235 | J13: =IF(ISNUMBER(I13),IF(I13<=0.5,"X",IF(I13<=1,"Y","Z")),"Z") | K13: =H13&J13 | L13: AX
A14: SYN_FOODS_2_009_CA_1 | B14: FOODS | C14: CA_1 | D14: 10131 | E14: 59687.148 | F14: =E14/SUM($E$5:$E$84) | G14: =SUM($E$5:E14)/SUM($E$5:$E$84)-F14 | H14: =IF(E14<=0,"C",IF(G14<0.8,"A",IF(G14<0.95,"B","C"))) | I14: 0.086473266 | J14: =IF(ISNUMBER(I14),IF(I14<=0.5,"X",IF(I14<=1,"Y","Z")),"Z") | K14: =H14&J14 | L14: AX
A15: SYN_FOODS_1_007_CA_2 | B15: FOODS | C15: CA_2 | D15: 6712 | E15: 51626.68 | F15: =E15/SUM($E$5:$E$84) | G15: =SUM($E$5:E15)/SUM($E$5:$E$84)-F15 | H15: =IF(E15<=0,"C",IF(G15<0.8,"A",IF(G15<0.95,"B","C"))) | I15: 0.096323253 | J15: =IF(ISNUMBER(I15),IF(I15<=0.5,"X",IF(I15<=1,"Y","Z")),"Z") | K15: =H15&J15 | L15: AX
A16: SYN_HOBBIES_2_006_CA_2 | B16: HOBBIES | C16: CA_2 | D16: 3853 | E16: 50667.891 | F16: =E16/SUM($E$5:$E$84) | G16: =SUM($E$5:E16)/SUM($E$5:$E$84)-F16 | H16: =IF(E16<=0,"C",IF(G16<0.8,"A",IF(G16<0.95,"B","C"))) | I16: 0.11893107 | J16: =IF(ISNUMBER(I16),IF(I16<=0.5,"X",IF(I16<=1,"Y","Z")),"Z") | K16: =H16&J16 | L16: AX
A17: SYN_FOODS_2_009_CA_2 | B17: FOODS | C17: CA_2 | D17: 8268 | E17: 48958.928 | F17: =E17/SUM($E$5:$E$84) | G17: =SUM($E$5:E17)/SUM($E$5:$E$84)-F17 | H17: =IF(E17<=0,"C",IF(G17<0.8,"A",IF(G17<0.95,"B","C"))) | I17: 0.10570353 | J17: =IF(ISNUMBER(I17),IF(I17<=0.5,"X",IF(I17<=1,"Y","Z")),"Z") | K17: =H17&J17 | L17: AX
A18: SYN_FOODS_3_009_CA_1 | B18: FOODS | C18: CA_1 | D18: 6497 | E18: 48941.699 | F18: =E18/SUM($E$5:$E$84) | G18: =SUM($E$5:E18)/SUM($E$5:$E$84)-F18 | H18: =IF(E18<=0,"C",IF(G18<0.8,"A",IF(G18<0.95,"B","C"))) | I18: 0.11098637 | J18: =IF(ISNUMBER(I18),IF(I18<=0.5,"X",IF(I18<=1,"Y","Z")),"Z") | K18: =H18&J18 | L18: AX
A19: SYN_HOBBIES_2_004_CA_1 | B19: HOBBIES | C19: CA_1 | D19: 11510 | E19: 48845.56 | F19: =E19/SUM($E$5:$E$84) | G19: =SUM($E$5:E19)/SUM($E$5:$E$84)-F19 | H19: =IF(E19<=0,"C",IF(G19<0.8,"A",IF(G19<0.95,"B","C"))) | I19: 0.085250728 | J19: =IF(ISNUMBER(I19),IF(I19<=0.5,"X",IF(I19<=1,"Y","Z")),"Z") | K19: =H19&J19 | L19: AX
A20: SYN_FOODS_1_009_CA_2 | B20: FOODS | C20: CA_2 | D20: 6131 | E20: 47070.501 | F20: =E20/SUM($E$5:$E$84) | G20: =SUM($E$5:E20)/SUM($E$5:$E$84)-F20 | H20: =IF(E20<=0,"C",IF(G20<0.8,"A",IF(G20<0.95,"B","C"))) | I20: 0.11876766 | J20: =IF(ISNUMBER(I20),IF(I20<=0.5,"X",IF(I20<=1,"Y","Z")),"Z") | K20: =H20&J20 | L20: AX
... A84: SYN_FOODS_2_004_CA_2 | B84: FOODS | C84: CA_2 | D84: 61 | E84: 174.49999 | F84: =E84/SUM($E$5:$E$84) | G84: =SUM($E$5:E84)/SUM($E$5:$E$84)-F84 | H84: =IF(E84<=0,"C",IF(G84<0.8,"A",IF(G84<0.95,"B","C"))) | I84: 1.28254 | J84: =IF(ISNUMBER(I84),IF(I84<=0.5,"X",IF(I84<=1,"Y","Z")),"Z") | K84: =H84&J84 | L84: CZ

Sheet Forecasts
A1: Demand forecasts (MODELED, Python)
A2: 28-day forecasts after the last observed day. Holdout = final 28 observed days, never used for selection or tuning.
A4: Series | B4: Item | C4: Store | D4: Category | E4: Pattern | F4: Selected method | G4: mu (units/day) | H4: 28-day forecast | I4: sigma (daily error) | J4: Holdout MAE | K4: Holdout WAPE | L4: Seasonal-naive WAPE | M4: WAPE improvement vs naive
A5: SYN_FOODS_1_001_CA_1 | B5: SYN_FOODS_1_001 | C5: CA_1 | D5: FOODS | E5: erratic | F5: moving_average | G5: 4.4107143 | H5: 123.5 | I5: 3.8152737 | J5: 2.8928571 | K5: 0.60902256 | L5: 0.96992481 | M5: =IF(AND(ISNUMBER(K5),ISNUMBER(L5),L5>0),1-K5/L5,"n/a")
A6: SYN_FOODS_1_003_CA_1 | B6: SYN_FOODS_1_003 | C6: CA_1 | D6: FOODS | E6: intermittent | F6: moving_average | G6: 0.82142857 | H6: 23 | I6: 1.2127879 | J6: 0.82142857 | K6: 1 | L6: 1.7826087 | M6: =IF(AND(ISNUMBER(K6),ISNUMBER(L6),L6>0),1-K6/L6,"n/a")
A7: SYN_FOODS_1_008_CA_1 | B7: SYN_FOODS_1_008 | C7: CA_1 | D7: FOODS | E7: lumpy | F7: gbm | G7: 2.3719318 | H7: 66.41409 | I7: 2.5867007 | J7: 1.3670423 | K7: 0.60757435 | L7: 0.87301587 | M7: =IF(AND(ISNUMBER(K7),ISNUMBER(L7),L7>0),1-K7/L7,"n/a")
A8: SYN_FOODS_1_009_CA_1 | B8: SYN_FOODS_1_009 | C8: CA_1 | D8: FOODS | E8: smooth | F8: moving_average | G8: 13.732143 | H8: 384.5 | I8: 4.2795417 | J8: 4.4234694 | K8: 0.31839882 | L8: 0.3470437 | M8: =IF(AND(ISNUMBER(K8),ISNUMBER(L8),L8>0),1-K8/L8,"n/a")
A9: SYN_FOODS_2_004_CA_1 | B9: SYN_FOODS_2_004 | C9: CA_1 | D9: FOODS | E9: intermittent | F9: sba | G9: 0.97570145 | H9: 27.319641 | I9: 1.2478393 | J9: 0.98452125 | K9: 1.1486081 | L9: 1 | M9: =IF(AND(ISNUMBER(K9),ISNUMBER(L9),L9>0),1-K9/L9,"n/a")
A10: SYN_FOODS_2_005_CA_1 | B10: SYN_FOODS_2_005 | C10: CA_1 | D10: FOODS | E10: lumpy | F10: seasonal_ma | G10: 1.5 | H10: 42 | I10: 2.8946533 | J10: 2.3928571 | K10: 1.1964286 | L10: 1.4642857 | M10: =IF(AND(ISNUMBER(K10),ISNUMBER(L10),L10>0),1-K10/L10,"n/a")
A11: SYN_FOODS_2_006_CA_1 | B11: SYN_FOODS_2_006 | C11: CA_1 | D11: FOODS | E11: smooth | F11: sba | G11: 1.8661789 | H11: 52.253008 | I11: 1.4796865 | J11: 1.1063214 | K11: 0.51628332 | L11: 0.63333333 | M11: =IF(AND(ISNUMBER(K11),ISNUMBER(L11),L11>0),1-K11/L11,"n/a")
A12: SYN_FOODS_2_008_CA_1 | B12: SYN_FOODS_2_008 | C12: CA_1 | D12: FOODS | E12: intermittent | F12: sba | G12: 0.80871069 | H12: 22.643899 | I12: 1.0323858 | J12: 0.85714286 | K12: 1 | L12: 1.5 | M12: =IF(AND(ISNUMBER(K12),ISNUMBER(L12),L12>0),1-K12/L12,"n/a")
A13: SYN_FOODS_2_009_CA_1 | B13: SYN_FOODS_2_009 | C13: CA_1 | D13: FOODS | E13: smooth | F13: gbm | G13: 28.879864 | H13: 808.63619 | I13: 7.4940437 | J13: 5.289586 | K13: 0.19487948 | L13: 0.26315789 | M13: =IF(AND(ISNUMBER(K13),ISNUMBER(L13),L13>0),1-K13/L13,"n/a")
A14: SYN_FOODS_3_002_CA_1 | B14: SYN_FOODS_3_002 | C14: CA_1 | D14: FOODS | E14: erratic | F14: sba | G14: 2.03234 | H14: 56.905521 | I14: 2.2982293 | J14: 1.6691583 | K14: 0.80580057 | L14: 1.137931 | M14: =IF(AND(ISNUMBER(K14),ISNUMBER(L14),L14>0),1-K14/L14,"n/a")
A15: SYN_FOODS_3_003_CA_1 | B15: SYN_FOODS_3_003 | C15: CA_1 | D15: FOODS | E15: erratic | F15: sba | G15: 9.4936724 | H15: 265.82283 | I15: 8.2526851 | J15: 7.0033613 | K15: 0.73719593 | L15: 1.2180451 | M15: =IF(AND(ISNUMBER(K15),ISNUMBER(L15),L15>0),1-K15/L15,"n/a")
A16: SYN_FOODS_3_004_CA_1 | B16: SYN_FOODS_3_004 | C16: CA_1 | D16: FOODS | E16: smooth | F16: gbm | G16: 11.962105 | H16: 334.93895 | I16: 3.5501363 | J16: 2.950819 | K16: 0.25189919 | L16: 0.38414634 | M16: =IF(AND(ISNUMBER(K16),ISNUMBER(L16),L16>0),1-K16/L16,"n/a")
... A84: SYN_HOUSEHOLD_2_008_CA_2 | B84: SYN_HOUSEHOLD_2_008 | C84: CA_2 | D84: HOUSEHOLD | E84: erratic | F84: sba | G84: 3.7699695 | H84: 105.55914 | I84: 3.0720289 | J84: 2.7186085 | K84: 0.67965212 | L84: 0.89285714 | M84: =IF(AND(ISNUMBER(K84),ISNUMBER(L84),L84>0),1-K84/L84,"n/a")
A87: Holdout accuracy by method - model stores, all series (Python)
A88: Method | B88: Series | C88: MAE | D88: WAPE | E88: Bias | F88: MASE
A89: Gradient boosting | B89: 126 | C89: 2.3494068 | D89: 0.3642267 | E89: 0.001847808 | F89: 0.78995732
A90: Moving average | B90: 126 | C90: 2.4240464 | D90: 0.37579803 | E90: 0.0044601661 | F90: 0.82424238
A91: Croston-SBA | B91: 126 | C91: 2.4143794 | D91: 0.37429935 | E91: -0.015443497 | F91: 0.81573987
A92: Seasonal moving average | B92: 126 | C92: 2.4543651 | D92: 0.38049831 | E92: 0.0044601661 | F92: 0.83595791
A93: Seasonal naive | B93: 126 | C93: 3.0598073 | D93: 0.47435954 | E93: -0.010062838 | F93: 0.98822933
A94: Selected per series | B94: 126 | C94: 2.3813765 | D94: 0.36918295 | E94: 0.0036306753 | F94: 0.8214773

Sheet Safety Stock
A1: Safety stock (MODELED)
A2: Live formulas. mu and sigma come from the Python forecasting engine; lead times are SIMULATED supplier terms.
A4: Series | B4: Item | C4: Store | D4: Category | E4: Demand pattern | F4: mu: daily demand | G4: sigma: daily error | H4: Base lead time | I4: Base LT sd | J4: E[L] used | K4: sd(L) used | L4: R (days) | M4: P = E[L]+R | N4: sigma_P | O4: z | P4: SS (normal) | Q4: ROP (normal) | R4: Empirical ROP (Python, default P) | S4: Intermittent? | T4: ROP used | U4: Safety stock used | V4: Python ROP | W4: Check vs Python
A5: SYN_FOODS_1_001_CA_1 | B5: SYN_FOODS_1_001 | C5: CA_1 | D5: FOODS | E5: erratic | F5: 4.4107143 | G5: 3.8152737 | H5: 5 | I5: 1 | J5: =MAX(H5+Assumptions!$C$7,1) | K5: =I5*Assumptions!$C$8 | L5: =Assumptions!$C$6 | M5: =J5+L5 | N5: =SQRT(M5*G5^2+F5^2*K5^2) | O5: =Assumptions!$C$12 | P5: =O5*N5 | Q5: =F5*M5+P5 | S5: FALSE | T5: =IF(AND(S5,ISNUMBER(R5)),IF(R5>Q5,R5,Q5),Q5) | U5: =T5-F5*M5 | V5: 75.846416 | W5: =IF(ABS(T5-V5)<0.01,"OK","CHECK")
A6: SYN_FOODS_1_003_CA_1 | B6: SYN_FOODS_1_003 | C6: CA_1 | D6: FOODS | E6: intermittent | F6: 0.82142857 | G6: 1.2127879 | H6: 5 | I6: 1 | J6: =MAX(H6+Assumptions!$C$7,1) | K6: =I6*Assumptions!$C$8 | L6: =Assumptions!$C$6 | M6: =J6+L6 | N6: =SQRT(M6*G6^2+F6^2*K6^2) | O6: =Assumptions!$C$12 | P6: =O6*N6 | Q6: =F6*M6+P6 | R6: 17 | S6: TRUE | T6: =IF(AND(S6,ISNUMBER(R6)),IF(R6>Q6,R6,Q6),Q6) | U6: =T6-F6*M6 | V6: 17 | W6: =IF(ABS(T6-V6)<0.01,"OK","CHECK")
A7: SYN_FOODS_1_008_CA_1 | B7: SYN_FOODS_1_008 | C7: CA_1 | D7: FOODS | E7: lumpy | F7: 2.3719318 | G7: 2.5867007 | H7: 5 | I7: 1 | J7: =MAX(H7+Assumptions!$C$7,1) | K7: =I7*Assumptions!$C$8 | L7: =Assumptions!$C$6 | M7: =J7+L7 | N7: =SQRT(M7*G7^2+F7^2*K7^2) | O7: =Assumptions!$C$12 | P7: =O7*N7 | Q7: =F7*M7+P7 | R7: 45 | S7: TRUE | T7: =IF(AND(S7,ISNUMBER(R7)),IF(R7>Q7,R7,Q7),Q7) | U7: =T7-F7*M7 | V7: 45 | W7: =IF(ABS(T7-V7)<0.01,"OK","CHECK")
A8: SYN_FOODS_1_009_CA_1 | B8: SYN_FOODS_1_009 | C8: CA_1 | D8: FOODS | E8: smooth | F8: 13.732143 | G8: 4.2795417 | H8: 5 | I8: 1 | J8: =MAX(H8+Assumptions!$C$7,1) | K8: =I8*Assumptions!$C$8 | L8: =Assumptions!$C$6 | M8: =J8+L8 | N8: =SQRT(M8*G8^2+F8^2*K8^2) | O8: =Assumptions!$C$12 | P8: =O8*N8 | Q8: =F8*M8+P8 | S8: FALSE | T8: =IF(AND(S8,ISNUMBER(R8)),IF(R8>Q8,R8,Q8),Q8) | U8: =T8-F8*M8 | V8: 198.02419 | W8: =IF(ABS(T8-V8)<0.01,"OK","CHECK")
A9: SYN_FOODS_2_004_CA_1 | B9: SYN_FOODS_2_004 | C9: CA_1 | D9: FOODS | E9: intermittent | F9: 0.97570145 | G9: 1.2478393 | H9: 6 | I9: 1.5 | J9: =MAX(H9+Assumptions!$C$7,1) | K9: =I9*Assumptions!$C$8 | L9: =Assumptions!$C$6 | M9: =J9+L9 | N9: =SQRT(M9*G9^2+F9^2*K9^2) | O9: =Assumptions!$C$12 | P9: =O9*N9 | Q9: =F9*M9+P9 | R9: 19 | S9: TRUE | T9: =IF(AND(S9,ISNUMBER(R9)),IF(R9>Q9,R9,Q9),Q9) | U9: =T9-F9*M9 | V9: 20.466262 | W9: =IF(ABS(T9-V9)<0.01,"OK","CHECK")
A10: SYN_FOODS_2_005_CA_1 | B10: SYN_FOODS_2_005 | C10: CA_1 | D10: FOODS | E10: lumpy | F10: 1.5 | G10: 2.8946533 | H10: 6 | I10: 1.5 | J10: =MAX(H10+Assumptions!$C$7,1) | K10: =I10*Assumptions!$C$8 | L10: =Assumptions!$C$6 | M10: =J10+L10 | N10: =SQRT(M10*G10^2+F10^2*K10^2) | O10: =Assumptions!$C$12 | P10: =O10*N10 | Q10: =F10*M10+P10 | R10: 48 | S10: TRUE | T10: =IF(AND(S10,ISNUMBER(R10)),IF(R10>Q10,R10,Q10),Q10) | U10: =T10-F10*M10 | V10: 48 | W10: =IF(ABS(T10-V10)<0.01,"OK","CHECK")
A11: SYN_FOODS_2_006_CA_1 | B11: SYN_FOODS_2_006 | C11: CA_1 | D11: FOODS | E11: smooth | F11: 1.8661789 | G11: 1.4796865 | H11: 6 | I11: 1.5 | J11: =MAX(H11+Assumptions!$C$7,1) | K11: =I11*Assumptions!$C$8 | L11: =Assumptions!$C$6 | M11: =J11+L11 | N11: =SQRT(M11*G11^2+F11^2*K11^2) | O11: =Assumptions!$C$12 | P11: =O11*N11 | Q11: =F11*M11+P11 | S11: FALSE | T11: =IF(AND(S11,ISNUMBER(R11)),IF(R11>Q11,R11,Q11),Q11) | U11: =T11-F11*M11 | V11: 34.170352 | W11: =IF(ABS(T11-V11)<0.01,"OK","CHECK")
A12: SYN_FOODS_2_008_CA_1 | B12: SYN_FOODS_2_008 | C12: CA_1 | D12: FOODS | E12: intermittent | F12: 0.80871069 | G12: 1.0323858 | H12: 6 | I12: 1.5 | J12: =MAX(H12+Assumptions!$C$7,1) | K12: =I12*Assumptions!$C$8 | L12: =Assumptions!$C$6 | M12: =J12+L12 | N12: =SQRT(M12*G12^2+F12^2*K12^2) | O12: =Assumptions!$C$12 | P12: =O12*N12 | Q12: =F12*M12+P12 | R12: 16 | S12: TRUE | T12: =IF(AND(S12,ISNUMBER(R12)),IF(R12>Q12,R12,Q12),Q12) | U12: =T12-F12*M12 | V12: 16.952835 | W12: =IF(ABS(T12-V12)<0.01,"OK","CHECK")
A13: SYN_FOODS_2_009_CA_1 | B13: SYN_FOODS_2_009 | C13: CA_1 | D13: FOODS | E13: smooth | F13: 28.879864 | G13: 7.4940437 | H13: 6 | I13: 1.5 | J13: =MAX(H13+Assumptions!$C$7,1) | K13: =I13*Assumptions!$C$8 | L13: =Assumptions!$C$6 | M13: =J13+L13 | N13: =SQRT(M13*G13^2+F13^2*K13^2) | O13: =Assumptions!$C$12 | P13: =O13*N13 | Q13: =F13*M13+P13 | S13: FALSE | T13: =IF(AND(S13,ISNUMBER(R13)),IF(R13>Q13,R13,Q13),Q13) | U13: =T13-F13*M13 | V13: 459.41753 | W13: =IF(ABS(T13-V13)<0.01,"OK","CHECK")
A14: SYN_FOODS_3_002_CA_1 | B14: SYN_FOODS_3_002 | C14: CA_1 | D14: FOODS | E14: erratic | F14: 2.03234 | G14: 2.2982293 | H14: 3 | I14: 0.8 | J14: =MAX(H14+Assumptions!$C$7,1) | K14: =I14*Assumptions!$C$8 | L14: =Assumptions!$C$6 | M14: =J14+L14 | N14: =SQRT(M14*G14^2+F14^2*K14^2) | O14: =Assumptions!$C$12 | P14: =O14*N14 | Q14: =F14*M14+P14 | S14: FALSE | T14: =IF(AND(S14,ISNUMBER(R14)),IF(R14>Q14,R14,Q14),Q14) | U14: =T14-F14*M14 | V14: 32.573092 | W14: =IF(ABS(T14-V14)<0.01,"OK","CHECK")
A15: SYN_FOODS_3_003_CA_1 | B15: SYN_FOODS_3_003 | C15: CA_1 | D15: FOODS | E15: erratic | F15: 9.4936724 | G15: 8.2526851 | H15: 3 | I15: 0.8 | J15: =MAX(H15+Assumptions!$C$7,1) | K15: =I15*Assumptions!$C$8 | L15: =Assumptions!$C$6 | M15: =J15+L15 | N15: =SQRT(M15*G15^2+F15^2*K15^2) | O15: =Assumptions!$C$12 | P15: =O15*N15 | Q15: =F15*M15+P15 | S15: FALSE | T15: =IF(AND(S15,ISNUMBER(R15)),IF(R15>Q15,R15,Q15),Q15) | U15: =T15-F15*M15 | V15: 139.64381 | W15: =IF(ABS(T15-V15)<0.01,"OK","CHECK")
A16: SYN_FOODS_3_004_CA_1 | B16: SYN_FOODS_3_004 | C16: CA_1 | D16: FOODS | E16: smooth | F16: 11.962105 | G16: 3.5501363 | H16: 3 | I16: 0.8 | J16: =MAX(H16+Assumptions!$C$7,1) | K16: =I16*Assumptions!$C$8 | L16: =Assumptions!$C$6 | M16: =J16+L16 | N16: =SQRT(M16*G16^2+F16^2*K16^2) | O16: =Assumptions!$C$12 | P16: =O16*N16 | Q16: =F16*M16+P16 | S16: FALSE | T16: =IF(AND(S16,ISNUMBER(R16)),IF(R16>Q16,R16,Q16),Q16) | U16: =T16-F16*M16 | V16: 143.88549 | W16: =IF(ABS(T16-V16)<0.01,"OK","CHECK")
A17: SYN_FOODS_3_005_CA_1 | B17: SYN_FOODS_3_005 | C17: CA_1 | D17: FOODS | E17: smooth | F17: 21.611318 | G17: 4.7171296 | H17: 3 | I17: 0.8 | J17: =MAX(H17+Assumptions!$C$7,1) | K17: =I17*Assumptions!$C$8 | L17: =Assumptions!$C$6 | M17: =J17+L17 | N17: =SQRT(M17*G17^2+F17^2*K17^2) | O17: =Assumptions!$C$12 | P17: =O17*N17 | Q17: =F17*M17+P17 | S17: FALSE | T17: =IF(AND(S17,ISNUMBER(R17)),IF(R17>Q17,R17,Q17),Q17) | U17: =T17-F17*M17 | V17: 253.67295 | W17: =IF(ABS(T17-V17)<0.01,"OK","CHECK")
A18: SYN_FOODS_3_007_CA_1 | B18: SYN_FOODS_3_007 | C18: CA_1 | D18: FOODS | E18: smooth | F18: 7.7142857 | G18: 3.1437296 | H18: 3 | I18: 0.8 | J18: =MAX(H18+Assumptions!$C$7,1) | K18: =I18*Assumptions!$C$8 | L18: =Assumptions!$C$6 | M18: =J18+L18 | N18: =SQRT(M18*G18^2+F18^2*K18^2) | O18: =Assumptions!$C$12 | P18: =O18*N18 | Q18: =F18*M18+P18 | S18: FALSE | T18: =IF(AND(S18,ISNUMBER(R18)),IF(R18>Q18,R18,Q18),Q18) | U18: =T18-F18*M18 | V18: 96.389534 | W18: =IF(ABS(T18-V18)<0.01,"OK","CHECK")
A19: SYN_FOODS_3_008_CA_1 | B19: SYN_FOODS_3_008 | C19: CA_1 | D19: FOODS | E19: intermittent | F19: 0.58928571 | G19: 1.0309311 | H19: 3 | I19: 0.8 | J19: =MAX(H19+Assumptions!$C$7,1) | K19: =I19*Assumptions!$C$8 | L19: =Assumptions!$C$6 | M19: =J19+L19 | N19: =SQRT(M19*G19^2+F19^2*K19^2) | O19: =Assumptions!$C$12 | P19: =O19*N19 | Q19: =F19*M19+P19 | R19: 13 | S19: TRUE | T19: =IF(AND(S19,ISNUMBER(R19)),IF(R19>Q19,R19,Q19),Q19) | U19: =T19-F19*M19 | V19: 13 | W19: =IF(ABS(T19-V19)<0.01,"OK","CHECK")
A20: SYN_FOODS_3_009_CA_1 | B20: SYN_FOODS_3_009 | C20: CA_1 | D20: FOODS | E20: smooth | F20: 18.088123 | G20: 4.7477322 | H20: 3 | I20: 0.8 | J20: =MAX(H20+Assumptions!$C$7,1) | K20: =I20*Assumptions!$C$8 | L20: =Assumptions!$C$6 | M20: =J20+L20 | N20: =SQRT(M20*G20^2+F20^2*K20^2) | O20: =Assumptions!$C$12 | P20: =O20*N20 | Q20: =F20*M20+P20 | S20: FALSE | T20: =IF(AND(S20,ISNUMBER(R20)),IF(R20>Q20,R20,Q20),Q20) | U20: =T20-F20*M20 | V20: 215.17968 | W20: =IF(ABS(T20-V20)<0.01,"OK","CHECK")
A21: SYN_HOBBIES_1_001_CA_1 | B21: SYN_HOBBIES_1_001 | C21: CA_1 | D21: HOBBIES | E21: erratic | F21: 4.7888728 | G21: 4.1314027 | H21: 14 | I21: 4 | J21: =MAX(H21+Assumptions!$C$7,1) | K21: =I21*Assumptions!$C$8 | L21: =Assumptions!$C$6 | M21: =J21+L21 | N21: =SQRT(M21*G21^2+F21^2*K21^2) | O21: =Assumptions!$C$12 | P21: =O21*N21 | Q21: =F21*M21+P21 | S21: FALSE | T21: =IF(AND(S21,ISNUMBER(R21)),IF(R21>Q21,R21,Q21),Q21) | U21: =T21-F21*M21 | V21: 144.8667 | W21: =IF(ABS(T21-V21)<0.01,"OK","CHECK")
A22: SYN_HOBBIES_1_003_CA_1 | B22: SYN_HOBBIES_1_003 | C22: CA_1 | D22: HOBBIES | E22: lumpy | F22: 0.85714286 | G22: 2.4142434 | H22: 14 | I22: 4 | J22: =MAX(H22+Assumptions!$C$7,1) | K22: =I22*Assumptions!$C$8 | L22: =Assumptions!$C$6 | M22: =J22+L22 | N22: =SQRT(M22*G22^2+F22^2*K22^2) | O22: =Assumptions!$C$12 | P22: =O22*N22 | Q22: =F22*M22+P22 | R22: 30 | S22: TRUE | T22: =IF(AND(S22,ISNUMBER(R22)),IF(R22>Q22,R22,Q22),Q22) | U22: =T22-F22*M22 | V22: 37.051574 | W22: =IF(ABS(T22-V22)<0.01,"OK","CHECK")
A23: SYN_HOBBIES_1_004_CA_1 | B23: SYN_HOBBIES_1_004 | C23: CA_1 | D23: HOBBIES | E23: intermittent | F23: 0.51785714 | G23: 0.87116507 | H23: 14 | I23: 4 | J23: =MAX(H23+Assumptions!$C$7,1) | K23: =I23*Assumptions!$C$8 | L23: =Assumptions!$C$6 | M23: =J23+L23 | N23: =SQRT(M23*G23^2+F23^2*K23^2) | O23: =Assumptions!$C$12 | P23: =O23*N23 | Q23: =F23*M23+P23 | R23: 17 | S23: TRUE | T23: =IF(AND(S23,ISNUMBER(R23)),IF(R23>Q23,R23,Q23),Q23) | U23: =T23-F23*M23 | V23: 18.272877 | W23: =IF(ABS(T23-V23)<0.01,"OK","CHECK")
A24: SYN_HOBBIES_1_005_CA_1 | B24: SYN_HOBBIES_1_005 | C24: CA_1 | D24: HOBBIES | E24: intermittent | F24: 0.14285714 | G24: 1.0106575 | H24: 14 | I24: 4 | J24: =MAX(H24+Assumptions!$C$7,1) | K24: =I24*Assumptions!$C$8 | L24: =Assumptions!$C$6 | M24: =J24+L24 | N24: =SQRT(M24*G24^2+F24^2*K24^2) | O24: =Assumptions!$C$12 | P24: =O24*N24 | Q24: =F24*M24+P24 | R24: 15 | S24: TRUE | T24: =IF(AND(S24,ISNUMBER(R24)),IF(R24>Q24,R24,Q24),Q24) | U24: =T24-F24*M24 | V24: 15 | W24: =IF(ABS(T24-V24)<0.01,"OK","CHECK")
A25: SYN_HOBBIES_1_006_CA_1 | B25: SYN_HOBBIES_1_006 | C25: CA_1 | D25: HOBBIES | E25: lumpy | F25: 0.71428571 | G25: 2.8422828 | H25: 14 | I25: 4 | J25: =MAX(H25+Assumptions!$C$7,1) | K25: =I25*Assumptions!$C$8 | L25: =Assumptions!$C$6 | M25: =J25+L25 | N25: =SQRT(M25*G25^2+F25^2*K25^2) | O25: =Assumptions!$C$12 | P25: =O25*N25 | Q25: =F25*M25+P25 | R25: 49 | S25: TRUE | T25: =IF(AND(S25,ISNUMBER(R25)),IF(R25>Q25,R25,Q25),Q25) | U25: =T25-F25*M25 | V25: 49 | W25: =IF(ABS(T25-V25)<0.01,"OK","CHECK")
A26: SYN_HOBBIES_1_007_CA_1 | B26: SYN_HOBBIES_1_007 | C26: CA_1 | D26: HOBBIES | E26: lumpy | F26: 0.94671798 | G26: 1.3130445 | H26: 14 | I26: 4 | J26: =MAX(H26+Assumptions!$C$7,1) | K26: =I26*Assumptions!$C$8 | L26: =Assumptions!$C$6 | M26: =J26+L26 | N26: =SQRT(M26*G26^2+F26^2*K26^2) | O26: =Assumptions!$C$12 | P26: =O26*N26 | Q26: =F26*M26+P26 | R26: 30 | S26: TRUE | T26: =IF(AND(S26,ISNUMBER(R26)),IF(R26>Q26,R26,Q26),Q26) | U26: =T26-F26*M26 | V26: 31.575305 | W26: =IF(ABS(T26-V26)<0.01,"OK","CHECK")
A27: SYN_HOBBIES_1_009_CA_1 | B27: SYN_HOBBIES_1_009 | C27: CA_1 | D27: HOBBIES | E27: smooth | F27: 11.911468 | G27: 3.6372416 | H27: 14 | I27: 4 | J27: =MAX(H27+Assumptions!$C$7,1) | K27: =I27*Assumptions!$C$8 | L27: =Assumptions!$C$6 | M27: =J27+L27 | N27: =SQRT(M27*G27^2+F27^2*K27^2) | O27: =Assumptions!$C$12 | P27: =O27*N27 | Q27: =F27*M27+P27 | S27: FALSE | T27: =IF(AND(S27,ISNUMBER(R27)),IF(R27>Q27,R27,Q27),Q27) | U27: =T27-F27*M27 | V27: 333.16844 | W27: =IF(ABS(T27-V27)<0.01,"OK","CHECK")
A28: SYN_HOBBIES_2_001_CA_1 | B28: SYN_HOBBIES_2_001 | C28: CA_1 | D28: HOBBIES | E28: erratic | F28: 2.9432485 | G28: 3.7022584 | H28: 14 | I28: 4 | J28: =MAX(H28+Assumptions!$C$7,1) | K28: =I28*Assumptions!$C$8 | L28: =Assumptions!$C$6 | M28: =J28+L28 | N28: =SQRT(M28*G28^2+F28^2*K28^2) | O28: =Assumptions!$C$12 | P28: =O28*N28 | Q28: =F28*M28+P28 | S28: FALSE | T28: =IF(AND(S28,ISNUMBER(R28)),IF(R28>Q28,R28,Q28),Q28) | U28: =T28-F28*M28 | V28: 95.77532 | W28: =IF(ABS(T28-V28)<0.01,"OK","CHECK")
A29: SYN_HOBBIES_2_002_CA_1 | B29: SYN_HOBBIES_2_002 | C29: CA_1 | D29: HOBBIES | E29: intermittent | F29: 0.55357143 | G29: 1.0194536 | H29: 14 | I29: 4 | J29: =MAX(H29+Assumptions!$C$7,1) | K29: =I29*Assumptions!$C$8 | L29: =Assumptions!$C$6 | M29: =J29+L29 | N29: =SQRT(M29*G29^2+F29^2*K29^2) | O29: =Assumptions!$C$12 | P29: =O29*N29 | Q29: =F29*M29+P29 | R29: 18 | S29: TRUE | T29: =IF(AND(S29,ISNUMBER(R29)),IF(R29>Q29,R29,Q29),Q29) | U29: =T29-F29*M29 | V29: 20.12876 | W29: =IF(ABS(T29-V29)<0.01,"OK","CHECK")
A30: SYN_HOBBIES_2_004_CA_1 | B30: SYN_HOBBIES_2_004 | C30: CA_1 | D30: HOBBIES | E30: smooth | F30: 32.111659 | G30: 7.8492385 | H30: 14 | I30: 4 | J30: =MAX(H30+Assumptions!$C$7,1) | K30: =I30*Assumptions!$C$8 | L30: =Assumptions!$C$6 | M30: =J30+L30 | N30: =SQRT(M30*G30^2+F30^2*K30^2) | O30: =Assumptions!$C$12 | P30: =O30*N30 | Q30: =F30*M30+P30 | S30: FALSE | T30: =IF(AND(S30,ISNUMBER(R30)),IF(R30>Q30,R30,Q30),Q30) | U30: =T30-F30*M30 | V30: 893.74858 | W30: =IF(ABS(T30-V30)<0.01,"OK","CHECK")
A31: SYN_HOBBIES_2_005_CA_1 | B31: SYN_HOBBIES_2_005 | C31: CA_1 | D31: HOBBIES | E31: smooth | F31: 25.796105 | G31: 6.5008046 | H31: 14 | I31: 4 | J31: =MAX(H31+Assumptions!$C$7,1) | K31: =I31*Assumptions!$C$8 | L31: =Assumptions!$C$6 | M31: =J31+L31 | N31: =SQRT(M31*G31^2+F31^2*K31^2) | O31: =Assumptions!$C$12 | P31: =O31*N31 | Q31: =F31*M31+P31 | S31: FALSE | T31: =IF(AND(S31,ISNUMBER(R31)),IF(R31>Q31,R31,Q31),Q31) | U31: =T31-F31*M31 | V31: 718.37345 | W31: =IF(ABS(T31-V31)<0.01,"OK","CHECK")
A32: SYN_HOBBIES_2_006_CA_1 | B32: SYN_HOBBIES_2_006 | C32: CA_1 | D32: HOBBIES | E32: smooth | F32: 29.106677 | G32: 6.6856602 | H32: 14 | I32: 4 | J32: =MAX(H32+Assumptions!$C$7,1) | K32: =I32*Assumptions!$C$8 | L32: =Assumptions!$C$6 | M32: =J32+L32 | N32: =SQRT(M32*G32^2+F32^2*K32^2) | O32: =Assumptions!$C$12 | P32: =O32*N32 | Q32: =F32*M32+P32 | S32: FALSE | T32: =IF(AND(S32,ISNUMBER(R32)),IF(R32>Q32,R32,Q32),Q32) | U32: =T32-F32*M32 | V32: 809.26473 | W32: =IF(ABS(T32-V32)<0.01,"OK","CHECK")
A33: SYN_HOBBIES_2_007_CA_1 | B33: SYN_HOBBIES_2_007 | C33: CA_1 | D33: HOBBIES | E33: smooth | F33: 1.413095 | G33: 1.0022149 | H33: 14 | I33: 4 | J33: =MAX(H33+Assumptions!$C$7,1) | K33: =I33*Assumptions!$C$8 | L33: =Assumptions!$C$6 | M33: =J33+L33 | N33: =SQRT(M33*G33^2+F33^2*K33^2) | O33: =Assumptions!$C$12 | P33: =O33*N33 | Q33: =F33*M33+P33 | S33: FALSE | T33: =IF(AND(S33,ISNUMBER(R33)),IF(R33>Q33,R33,Q33),Q33) | U33: =T33-F33*M33 | V33: 41.654513 | W33: =IF(ABS(T33-V33)<0.01,"OK","CHECK")
A34: SYN_HOBBIES_2_009_CA_1 | B34: SYN_HOBBIES_2_009 | C34: CA_1 | D34: HOBBIES | E34: smooth | F34: 5.4107143 | G34: 2.0288575 | H34: 14 | I34: 4 | J34: =MAX(H34+Assumptions!$C$7,1) | K34: =I34*Assumptions!$C$8 | L34: =Assumptions!$C$6 | M34: =J34+L34 | N34: =SQRT(M34*G34^2+F34^2*K34^2) | O34: =Assumptions!$C$12 | P34: =O34*N34 | Q34: =F34*M34+P34 | S34: FALSE | T34: =IF(AND(S34,ISNUMBER(R34)),IF(R34>Q34,R34,Q34),Q34) | U34: =T34-F34*M34 | V34: 152.37011 | W34: =IF(ABS(T34-V34)<0.01,"OK","CHECK")
A35: SYN_HOUSEHOLD_1_001_CA_1 | B35: SYN_HOUSEHOLD_1_001 | C35: CA_1 | D35: HOUSEHOLD | E35: intermittent | F35: 0.37451243 | G35: 0.99713951 | H35: 7 | I35: 2 | J35: =MAX(H35+Assumptions!$C$7,1) | K35: =I35*Assumptions!$C$8 | L35: =Assumptions!$C$6 | M35: =J35+L35 | N35: =SQRT(M35*G35^2+F35^2*K35^2) | O35: =Assumptions!$C$12 | P35: =O35*N35 | Q35: =F35*M35+P35 | R35: 11 | S35: TRUE | T35: =IF(AND(S35,ISNUMBER(R35)),IF(R35>Q35,R35,Q35),Q35) | U35: =T35-F35*M35 | V35: 11.502498 | W35: =IF(ABS(T35-V35)<0.01,"OK","CHECK")
A36: SYN_HOUSEHOLD_1_007_CA_1 | B36: SYN_HOUSEHOLD_1_007 | C36: CA_1 | D36: HOUSEHOLD | E36: erratic | F36: 11.169627 | G36: 7.2485525 | H36: 7 | I36: 2 | J36: =MAX(H36+Assumptions!$C$7,1) | K36: =I36*Assumptions!$C$8 | L36: =Assumptions!$C$6 | M36: =J36+L36 | N36: =SQRT(M36*G36^2+F36^2*K36^2) | O36: =Assumptions!$C$12 | P36: =O36*N36 | Q36: =F36*M36+P36 | S36: FALSE | T36: =IF(AND(S36,ISNUMBER(R36)),IF(R36>Q36,R36,Q36),Q36) | U36: =T36-F36*M36 | V36: 214.17035 | W36: =IF(ABS(T36-V36)<0.01,"OK","CHECK")
A37: SYN_HOUSEHOLD_1_008_CA_1 | B37: SYN_HOUSEHOLD_1_008 | C37: CA_1 | D37: HOUSEHOLD | E37: smooth | F37: 2.895603 | G37: 1.8722902 | H37: 7 | I37: 2 | J37: =MAX(H37+Assumptions!$C$7,1) | K37: =I37*Assumptions!$C$8 | L37: =Assumptions!$C$6 | M37: =J37+L37 | N37: =SQRT(M37*G37^2+F37^2*K37^2) | O37: =Assumptions!$C$12 | P37: =O37*N37 | Q37: =F37*M37+P37 | S37: FALSE | T37: =IF(AND(S37,ISNUMBER(R37)),IF(R37>Q37,R37,Q37),Q37) | U37: =T37-F37*M37 | V37: 55.488945 | W37: =IF(ABS(T37-V37)<0.01,"OK","CHECK")
A38: SYN_HOUSEHOLD_1_009_CA_1 | B38: SYN_HOUSEHOLD_1_009 | C38: CA_1 | D38: HOUSEHOLD | E38: smooth | F38: 13.375 | G38: 4.2345307 | H38: 7 | I38: 2 | J38: =MAX(H38+Assumptions!$C$7,1) | K38: =I38*Assumptions!$C$8 | L38: =Assumptions!$C$6 | M38: =J38+L38 | N38: =SQRT(M38*G38^2+F38^2*K38^2) | O38: =Assumptions!$C$12 | P38: =O38*N38 | Q38: =F38*M38+P38 | S38: FALSE | T38: =IF(AND(S38,ISNUMBER(R38)),IF(R38>Q38,R38,Q38),Q38) | U38: =T38-F38*M38 | V38: 238.38881 | W38: =IF(ABS(T38-V38)<0.01,"OK","CHECK")
A39: SYN_HOUSEHOLD_2_001_CA_1 | B39: SYN_HOUSEHOLD_2_001 | C39: CA_1 | D39: HOUSEHOLD | E39: smooth | F39: 21.966979 | G39: 5.3095421 | H39: 10 | I39: 3.5 | J39: =MAX(H39+Assumptions!$C$7,1) | K39: =I39*Assumptions!$C$8 | L39: =Assumptions!$C$6 | M39: =J39+L39 | N39: =SQRT(M39*G39^2+F39^2*K39^2) | O39: =Assumptions!$C$12 | P39: =O39*N39 | Q39: =F39*M39+P39 | S39: FALSE | T39: =IF(AND(S39,ISNUMBER(R39)),IF(R39>Q39,R39,Q39),Q39) | U39: =T39-F39*M39 | V39: 504.92888 | W39: =IF(ABS(T39-V39)<0.01,"OK","CHECK")
A40: SYN_HOUSEHOLD_2_003_CA_1 | B40: SYN_HOUSEHOLD_2_003 | C40: CA_1 | D40: HOUSEHOLD | E40: erratic | F40: 4.9993949 | G40: 5.0481004 | H40: 10 | I40: 3.5 | J40: =MAX(H40+Assumptions!$C$7,1) | K40: =I40*Assumptions!$C$8 | L40: =Assumptions!$C$6 | M40: =J40+L40 | N40: =SQRT(M40*G40^2+F40^2*K40^2) | O40: =Assumptions!$C$12 | P40: =O40*N40 | Q40: =F40*M40+P40 | S40: FALSE | T40: =IF(AND(S40,ISNUMBER(R40)),IF(R40>Q40,R40,Q40),Q40) | U40: =T40-F40*M40 | V40: 129.71619 | W40: =IF(ABS(T40-V40)<0.01,"OK","CHECK")
A41: SYN_HOUSEHOLD_2_004_CA_1 | B41: SYN_HOUSEHOLD_2_004 | C41: CA_1 | D41: HOUSEHOLD | E41: smooth | F41: 17.413932 | G41: 4.814204 | H41: 10 | I41: 3.5 | J41: =MAX(H41+Assumptions!$C$7,1) | K41: =I41*Assumptions!$C$8 | L41: =Assumptions!$C$6 | M41: =J41+L41 | N41: =SQRT(M41*G41^2+F41^2*K41^2) | O41: =Assumptions!$C$12 | P41: =O41*N41 | Q41: =F41*M41+P41 | S41: FALSE | T41: =IF(AND(S41,ISNUMBER(R41)),IF(R41>Q41,R41,Q41),Q41) | U41: =T41-F41*M41 | V41: 401.47122 | W41: =IF(ABS(T41-V41)<0.01,"OK","CHECK")
A42: SYN_HOUSEHOLD_2_005_CA_1 | B42: SYN_HOUSEHOLD_2_005 | C42: CA_1 | D42: HOUSEHOLD | E42: intermittent | F42: 1 | G42: 0.9935378 | H42: 10 | I42: 3.5 | J42: =MAX(H42+Assumptions!$C$7,1) | K42: =I42*Assumptions!$C$8 | L42: =Assumptions!$C$6 | M42: =J42+L42 | N42: =SQRT(M42*G42^2+F42^2*K42^2) | O42: =Assumptions!$C$12 | P42: =O42*N42 | Q42: =F42*M42+P42 | R42: 26 | S42: TRUE | T42: =IF(AND(S42,ISNUMBER(R42)),IF(R42>Q42,R42,Q42),Q42) | U42: =T42-F42*M42 | V42: 26 | W42: =IF(ABS(T42-V42)<0.01,"OK","CHECK")
A43: SYN_HOUSEHOLD_2_006_CA_1 | B43: SYN_HOUSEHOLD_2_006 | C43: CA_1 | D43: HOUSEHOLD | E43: erratic | F43: 5.8902411 | G43: 7.1839387 | H43: 10 | I43: 3.5 | J43: =MAX(H43+Assumptions!$C$7,1) | K43: =I43*Assumptions!$C$8 | L43: =Assumptions!$C$6 | M43: =J43+L43 | N43: =SQRT(M43*G43^2+F43^2*K43^2) | O43: =Assumptions!$C$12 | P43: =O43*N43 | Q43: =F43*M43+P43 | S43: FALSE | T43: =IF(AND(S43,ISNUMBER(R43)),IF(R43>Q43,R43,Q43),Q43) | U43: =T43-F43*M43 | V43: 159.49408 | W43: =IF(ABS(T43-V43)<0.01,"OK","CHECK")
A44: SYN_HOUSEHOLD_2_007_CA_1 | B44: SYN_HOUSEHOLD_2_007 | C44: CA_1 | D44: HOUSEHOLD | E44: intermittent | F44: 0.875 | G44: 1.1348773 | H44: 10 | I44: 3.5 | J44: =MAX(H44+Assumptions!$C$7,1) | K44: =I44*Assumptions!$C$8 | L44: =Assumptions!$C$6 | M44: =J44+L44 | N44: =SQRT(M44*G44^2+F44^2*K44^2) | O44: =Assumptions!$C$12 | P44: =O44*N44 | Q44: =F44*M44+P44 | R44: 22 | S44: TRUE | T44: =IF(AND(S44,ISNUMBER(R44)),IF(R44>Q44,R44,Q44),Q44) | U44: =T44-F44*M44 | V44: 24.073541 | W44: =IF(ABS(T44-V44)<0.01,"OK","CHECK")
A45: SYN_FOODS_1_001_CA_2 | B45: SYN_FOODS_1_001 | C45: CA_2 | D45: FOODS | E45: erratic | F45: 7.8795242 | G45: 5.6060865 | H45: 5 | I45: 1 | J45: =MAX(H45+Assumptions!$C$7,1) | K45: =I45*Assumptions!$C$8 | L45: =Assumptions!$C$6 | M45: =J45+L45 | N45: =SQRT(M45*G45^2+F45^2*K45^2) | O45: =Assumptions!$C$12 | P45: =O45*N45 | Q45: =F45*M45+P45 | S45: FALSE | T45: =IF(AND(S45,ISNUMBER(R45)),IF(R45>Q45,R45,Q45),Q45) | U45: =T45-F45*M45 | V45: 129.02665 | W45: =IF(ABS(T45-V45)<0.01,"OK","CHECK")
A46: SYN_FOODS_1_002_CA_2 | B46: SYN_FOODS_1_002 | C46: CA_2 | D46: FOODS | E46: smooth | F46: 6.9683809 | G46: 2.9076837 | H46: 5 | I46: 1 | J46: =MAX(H46+Assumptions!$C$7,1) | K46: =I46*Assumptions!$C$8 | L46: =Assumptions!$C$6 | M46: =J46+L46 | N46: =SQRT(M46*G46^2+F46^2*K46^2) | O46: =Assumptions!$C$12 | P46: =O46*N46 | Q46: =F46*M46+P46 | S46: FALSE | T46: =IF(AND(S46,ISNUMBER(R46)),IF(R46>Q46,R46,Q46),Q46) | U46: =T46-F46*M46 | V46: 103.76676 | W46: =IF(ABS(T46-V46)<0.01,"OK","CHECK")
A47: SYN_FOODS_1_005_CA_2 | B47: SYN_FOODS_1_005 | C47: CA_2 | D47: FOODS | E47: lumpy | F47: 1.4384166 | G47: 2.5631073 | H47: 5 | I47: 1 | J47: =MAX(H47+Assumptions!$C$7,1) | K47: =I47*Assumptions!$C$8 | L47: =Assumptions!$C$6 | M47: =J47+L47 | N47: =SQRT(M47*G47^2+F47^2*K47^2) | O47: =Assumptions!$C$12 | P47: =O47*N47 | Q47: =F47*M47+P47 | R47: 31 | S47: TRUE | T47: =IF(AND(S47,ISNUMBER(R47)),IF(R47>Q47,R47,Q47),Q47) | U47: =T47-F47*M47 | V47: 32.05584 | W47: =IF(ABS(T47-V47)<0.01,"OK","CHECK")
A48: SYN_FOODS_1_006_CA_2 | B48: SYN_FOODS_1_006 | C48: CA_2 | D48: FOODS | E48: lumpy | F48: 0.96428571 | G48: 1.8094847 | H48: 5 | I48: 1 | J48: =MAX(H48+Assumptions!$C$7,1) | K48: =I48*Assumptions!$C$8 | L48: =Assumptions!$C$6 | M48: =J48+L48 | N48: =SQRT(M48*G48^2+F48^2*K48^2) | O48: =Assumptions!$C$12 | P48: =O48*N48 | Q48: =F48*M48+P48 | R48: 26 | S48: TRUE | T48: =IF(AND(S48,ISNUMBER(R48)),IF(R48>Q48,R48,Q48),Q48) | U48: =T48-F48*M48 | V48: 26 | W48: =IF(ABS(T48-V48)<0.01,"OK","CHECK")
A49: SYN_FOODS_1_007_CA_2 | B49: SYN_FOODS_1_007 | C49: CA_2 | D49: FOODS | E49: smooth | F49: 18.142857 | G49: 5.7777282 | H49: 5 | I49: 1 | J49: =MAX(H49+Assumptions!$C$7,1) | K49: =I49*Assumptions!$C$8 | L49: =Assumptions!$C$6 | M49: =J49+L49 | N49: =SQRT(M49*G49^2+F49^2*K49^2) | O49: =Assumptions!$C$12 | P49: =O49*N49 | Q49: =F49*M49+P49 | S49: FALSE | T49: =IF(AND(S49,ISNUMBER(R49)),IF(R49>Q49,R49,Q49),Q49) | U49: =T49-F49*M49 | V49: 262.14814 | W49: =IF(ABS(T49-V49)<0.01,"OK","CHECK")
A50: SYN_FOODS_1_009_CA_2 | B50: SYN_FOODS_1_009 | C50: CA_2 | D50: FOODS | E50: smooth | F50: 16.975833 | G50: 5.1586119 | H50: 5 | I50: 1 | J50: =MAX(H50+Assumptions!$C$7,1) | K50: =I50*Assumptions!$C$8 | L50: =Assumptions!$C$6 | M50: =J50+L50 | N50: =SQRT(M50*G50^2+F50^2*K50^2) | O50: =Assumptions!$C$12 | P50: =O50*N50 | Q50: =F50*M50+P50 | S50: FALSE | T50: =IF(AND(S50,ISNUMBER(R50)),IF(R50>Q50,R50,Q50),Q50) | U50: =T50-F50*M50 | V50: 244.25202 | W50: =IF(ABS(T50-V50)<0.01,"OK","CHECK")
A51: SYN_FOODS_2_003_CA_2 | B51: SYN_FOODS_2_003 | C51: CA_2 | D51: FOODS | E51: smooth | F51: 5.0648804 | G51: 2.6710652 | H51: 6 | I51: 1.5 | J51: =MAX(H51+Assumptions!$C$7,1) | K51: =I51*Assumptions!$C$8 | L51: =Assumptions!$C$6 | M51: =J51+L51 | N51: =SQRT(M51*G51^2+F51^2*K51^2) | O51: =Assumptions!$C$12 | P51: =O51*N51 | Q51: =F51*M51+P51 | S51: FALSE | T51: =IF(AND(S51,ISNUMBER(R51)),IF(R51>Q51,R51,Q51),Q51) | U51: =T51-F51*M51 | V51: 86.02017 | W51: =IF(ABS(T51-V51)<0.01,"OK","CHECK")
A52: SYN_FOODS_2_004_CA_2 | B52: SYN_FOODS_2_004 | C52: CA_2 | D52: FOODS | E52: intermittent | F52: 0.14285714 | G52: 0.38959686 | H52: 6 | I52: 1.5 | J52: =MAX(H52+Assumptions!$C$7,1) | K52: =I52*Assumptions!$C$8 | L52: =Assumptions!$C$6 | M52: =J52+L52 | N52: =SQRT(M52*G52^2+F52^2*K52^2) | O52: =Assumptions!$C$12 | P52: =O52*N52 | Q52: =F52*M52+P52 | R52: 5 | S52: TRUE | T52: =IF(AND(S52,ISNUMBER(R52)),IF(R52>Q52,R52,Q52),Q52) | U52: =T52-F52*M52 | V52: 5 | W52: =IF(ABS(T52-V52)<0.01,"OK","CHECK")
A53: SYN_FOODS_2_005_CA_2 | B53: SYN_FOODS_2_005 | C53: CA_2 | D53: FOODS | E53: lumpy | F53: 0.90391099 | G53: 2.6977391 | H53: 6 | I53: 1.5 | J53: =MAX(H53+Assumptions!$C$7,1) | K53: =I53*Assumptions!$C$8 | L53: =Assumptions!$C$6 | M53: =J53+L53 | N53: =SQRT(M53*G53^2+F53^2*K53^2) | O53: =Assumptions!$C$12 | P53: =O53*N53 | Q53: =F53*M53+P53 | R53: 23 | S53: TRUE | T53: =IF(AND(S53,ISNUMBER(R53)),IF(R53>Q53,R53,Q53),Q53) | U53: =T53-F53*M53 | V53: 27.904757 | W53: =IF(ABS(T53-V53)<0.01,"OK","CHECK")
A54: SYN_FOODS_2_009_CA_2 | B54: SYN_FOODS_2_009 | C54: CA_2 | D54: FOODS | E54: smooth | F54: 22.815561 | G54: 6.1801838 | H54: 6 | I54: 1.5 | J54: =MAX(H54+Assumptions!$C$7,1) | K54: =I54*Assumptions!$C$8 | L54: =Assumptions!$C$6 | M54: =J54+L54 | N54: =SQRT(M54*G54^2+F54^2*K54^2) | O54: =Assumptions!$C$12 | P54: =O54*N54 | Q54: =F54*M54+P54 | S54: FALSE | T54: =IF(AND(S54,ISNUMBER(R54)),IF(R54>Q54,R54,Q54),Q54) | U54: =T54-F54*M54 | V54: 363.77534 | W54: =IF(ABS(T54-V54)<0.01,"OK","CHECK")
A55: SYN_FOODS_3_001_CA_2 | B55: SYN_FOODS_3_001 | C55: CA_2 | D55: FOODS | E55: intermittent | F55: 1.619355 | G55: 1.4686446 | H55: 3 | I55: 0.8 | J55: =MAX(H55+Assumptions!$C$7,1) | K55: =I55*Assumptions!$C$8 | L55: =Assumptions!$C$6 | M55: =J55+L55 | N55: =SQRT(M55*G55^2+F55^2*K55^2) | O55: =Assumptions!$C$12 | P55: =O55*N55 | Q55: =F55*M55+P55 | R55: 29 | S55: TRUE | T55: =IF(AND(S55,ISNUMBER(R55)),IF(R55>Q55,R55,Q55),Q55) | U55: =T55-F55*M55 | V55: 29 | W55: =IF(ABS(T55-V55)<0.01,"OK","CHECK")
A56: SYN_FOODS_3_002_CA_2 | B56: SYN_FOODS_3_002 | C56: CA_2 | D56: FOODS | E56: erratic | F56: 4.2876329 | G56: 4.475224 | H56: 3 | I56: 0.8 | J56: =MAX(H56+Assumptions!$C$7,1) | K56: =I56*Assumptions!$C$8 | L56: =Assumptions!$C$6 | M56: =J56+L56 | N56: =SQRT(M56*G56^2+F56^2*K56^2) | O56: =Assumptions!$C$12 | P56: =O56*N56 | Q56: =F56*M56+P56 | S56: FALSE | T56: =IF(AND(S56,ISNUMBER(R56)),IF(R56>Q56,R56,Q56),Q56) | U56: =T56-F56*M56 | V56: 66.828128 | W56: =IF(ABS(T56-V56)<0.01,"OK","CHECK")
A57: SYN_FOODS_3_003_CA_2 | B57: SYN_FOODS_3_003 | C57: CA_2 | D57: FOODS | E57: erratic | F57: 7.1442851 | G57: 7.0224736 | H57: 3 | I57: 0.8 | J57: =MAX(H57+Assumptions!$C$7,1) | K57: =I57*Assumptions!$C$8 | L57: =Assumptions!$C$6 | M57: =J57+L57 | N57: =SQRT(M57*G57^2+F57^2*K57^2) | O57: =Assumptions!$C$12 | P57: =O57*N57 | Q57: =F57*M57+P57 | S57: FALSE | T57: =IF(AND(S57,ISNUMBER(R57)),IF(R57>Q57,R57,Q57),Q57) | U57: =T57-F57*M57 | V57: 109.16051 | W57: =IF(ABS(T57-V57)<0.01,"OK","CHECK")
A58: SYN_FOODS_3_005_CA_2 | B58: SYN_FOODS_3_005 | C58: CA_2 | D58: FOODS | E58: smooth | F58: 18.803571 | G58: 5.2913339 | H58: 3 | I58: 0.8 | J58: =MAX(H58+Assumptions!$C$7,1) | K58: =I58*Assumptions!$C$8 | L58: =Assumptions!$C$6 | M58: =J58+L58 | N58: =SQRT(M58*G58^2+F58^2*K58^2) | O58: =Assumptions!$C$12 | P58: =O58*N58 | Q58: =F58*M58+P58 | S58: FALSE | T58: =IF(AND(S58,ISNUMBER(R58)),IF(R58>Q58,R58,Q58),Q58) | U58: =T58-F58*M58 | V58: 225.04564 | W58: =IF(ABS(T58-V58)<0.01,"OK","CHECK")
A59: SYN_FOODS_3_007_CA_2 | B59: SYN_FOODS_3_007 | C59: CA_2 | D59: FOODS | E59: smooth | F59: 22.206013 | G59: 5.2475077 | H59: 3 | I59: 0.8 | J59: =MAX(H59+Assumptions!$C$7,1) | K59: =I59*Assumptions!$C$8 | L59: =Assumptions!$C$6 | M59: =J59+L59 | N59: =SQRT(M59*G59^2+F59^2*K59^2) | O59: =Assumptions!$C$12 | P59: =O59*N59 | Q59: =F59*M59+P59 | S59: FALSE | T59: =IF(AND(S59,ISNUMBER(R59)),IF(R59>Q59,R59,Q59),Q59) | U59: =T59-F59*M59 | V59: 262.0457 | W59: =IF(ABS(T59-V59)<0.01,"OK","CHECK")
A60: SYN_FOODS_3_008_CA_2 | B60: SYN_FOODS_3_008 | C60: CA_2 | D60: FOODS | E60: intermittent | F60: 0.26785714 | G60: 0.79310646 | H60: 3 | I60: 0.8 | J60: =MAX(H60+Assumptions!$C$7,1) | K60: =I60*Assumptions!$C$8 | L60: =Assumptions!$C$6 | M60: =J60+L60 | N60: =SQRT(M60*G60^2+F60^2*K60^2) | O60: =Assumptions!$C$12 | P60: =O60*N60 | Q60: =F60*M60+P60 | R60: 9 | S60: TRUE | T60: =IF(AND(S60,ISNUMBER(R60)),IF(R60>Q60,R60,Q60),Q60) | U60: =T60-F60*M60 | V60: 9 | W60: =IF(ABS(T60-V60)<0.01,"OK","CHECK")
A61: SYN_HOBBIES_1_001_CA_2 | B61: SYN_HOBBIES_1_001 | C61: CA_2 | D61: HOBBIES | E61: lumpy | F61: 1.2638795 | G61: 1.460001 | H61: 14 | I61: 4 | J61: =MAX(H61+Assumptions!$C$7,1) | K61: =I61*Assumptions!$C$8 | L61: =Assumptions!$C$6 | M61: =J61+L61 | N61: =SQRT(M61*G61^2+F61^2*K61^2) | O61: =Assumptions!$C$12 | P61: =O61*N61 | Q61: =F61*M61+P61 | R61: 41 | S61: TRUE | T61: =IF(AND(S61,ISNUMBER(R61)),IF(R61>Q61,R61,Q61),Q61) | U61: =T61-F61*M61 | V61: 41 | W61: =IF(ABS(T61-V61)<0.01,"OK","CHECK")
A62: SYN_HOBBIES_1_002_CA_2 | B62: SYN_HOBBIES_1_002 | C62: CA_2 | D62: HOBBIES | E62: intermittent | F62: 0.375 | G62: 0.88124594 | H62: 14 | I62: 4 | J62: =MAX(H62+Assumptions!$C$7,1) | K62: =I62*Assumptions!$C$8 | L62: =Assumptions!$C$6 | M62: =J62+L62 | N62: =SQRT(M62*G62^2+F62^2*K62^2) | O62: =Assumptions!$C$12 | P62: =O62*N62 | Q62: =F62*M62+P62 | R62: 13 | S62: TRUE | T62: =IF(AND(S62,ISNUMBER(R62)),IF(R62>Q62,R62,Q62),Q62) | U62: =T62-F62*M62 | V62: 14.960957 | W62: =IF(ABS(T62-V62)<0.01,"OK","CHECK")
A63: SYN_HOBBIES_1_003_CA_2 | B63: SYN_HOBBIES_1_003 | C63: CA_2 | D63: HOBBIES | E63: lumpy | F63: 0 | G63: 2.7632796 | H63: 14 | I63: 4 | J63: =MAX(H63+Assumptions!$C$7,1) | K63: =I63*Assumptions!$C$8 | L63: =Assumptions!$C$6 | M63: =J63+L63 | N63: =SQRT(M63*G63^2+F63^2*K63^2) | O63: =Assumptions!$C$12 | P63: =O63*N63 | Q63: =F63*M63+P63 | R63: 32 | S63: TRUE | T63: =IF(AND(S63,ISNUMBER(R63)),IF(R63>Q63,R63,Q63),Q63) | U63: =T63-F63*M63 | V63: 32 | W63: =IF(ABS(T63-V63)<0.01,"OK","CHECK")
A64: SYN_HOBBIES_1_004_CA_2 | B64: SYN_HOBBIES_1_004 | C64: CA_2 | D64: HOBBIES | E64: intermittent | F64: 0.96278751 | G64: 1.1218576 | H64: 14 | I64: 4 | J64: =MAX(H64+Assumptions!$C$7,1) | K64: =I64*Assumptions!$C$8 | L64: =Assumptions!$C$6 | M64: =J64+L64 | N64: =SQRT(M64*G64^2+F64^2*K64^2) | O64: =Assumptions!$C$12 | P64: =O64*N64 | Q64: =F64*M64+P64 | R64: 24 | S64: TRUE | T64: =IF(AND(S64,ISNUMBER(R64)),IF(R64>Q64,R64,Q64),Q64) | U64: =T64-F64*M64 | V64: 30.784237 | W64: =IF(ABS(T64-V64)<0.01,"OK","CHECK")
A65: SYN_HOBBIES_1_005_CA_2 | B65: SYN_HOBBIES_1_005 | C65: CA_2 | D65: HOBBIES | E65: intermittent | F65: 0.96341431 | G65: 1.1126862 | H65: 14 | I65: 4 | J65: =MAX(H65+Assumptions!$C$7,1) | K65: =I65*Assumptions!$C$8 | L65: =Assumptions!$C$6 | M65: =J65+L65 | N65: =SQRT(M65*G65^2+F65^2*K65^2) | O65: =Assumptions!$C$12 | P65: =O65*N65 | Q65: =F65*M65+P65 | R65: 29 | S65: TRUE | T65: =IF(AND(S65,ISNUMBER(R65)),IF(R65>Q65,R65,Q65),Q65) | U65: =T65-F65*M65 | V65: 30.744639 | W65: =IF(ABS(T65-V65)<0.01,"OK","CHECK")
A66: SYN_HOBBIES_1_006_CA_2 | B66: SYN_HOBBIES_1_006 | C66: CA_2 | D66: HOBBIES | E66: lumpy | F66: 0.56917328 | G66: 1.7741507 | H66: 14 | I66: 4 | J66: =MAX(H66+Assumptions!$C$7,1) | K66: =I66*Assumptions!$C$8 | L66: =Assumptions!$C$6 | M66: =J66+L66 | N66: =SQRT(M66*G66^2+F66^2*K66^2) | O66: =Assumptions!$C$12 | P66: =O66*N66 | Q66: =F66*M66+P66 | R66: 23 | S66: TRUE | T66: =IF(AND(S66,ISNUMBER(R66)),IF(R66>Q66,R66,Q66),Q66) | U66: =T66-F66*M66 | V66: 25.840032 | W66: =IF(ABS(T66-V66)<0.01,"OK","CHECK")
A67: SYN_HOBBIES_1_008_CA_2 | B67: SYN_HOBBIES_1_008 | C67: CA_2 | D67: HOBBIES | E67: lumpy | F67: 0.57142857 | G67: 1.4681135 | H67: 14 | I67: 4 | J67: =MAX(H67+Assumptions!$C$7,1) | K67: =I67*Assumptions!$C$8 | L67: =Assumptions!$C$6 | M67: =J67+L67 | N67: =SQRT(M67*G67^2+F67^2*K67^2) | O67: =Assumptions!$C$12 | P67: =O67*N67 | Q67: =F67*M67+P67 | R67: 23 | S67: TRUE | T67: =IF(AND(S67,ISNUMBER(R67)),IF(R67>Q67,R67,Q67),Q67) | U67: =T67-F67*M67 | V67: 23.687375 | W67: =IF(ABS(T67-V67)<0.01,"OK","CHECK")
A68: SYN_HOBBIES_1_009_CA_2 | B68: SYN_HOBBIES_1_009 | C68: CA_2 | D68: HOBBIES | E68: smooth | F68: 3.0714286 | G68: 1.582429 | H68: 14 | I68: 4 | J68: =MAX(H68+Assumptions!$C$7,1) | K68: =I68*Assumptions!$C$8 | L68: =Assumptions!$C$6 | M68: =J68+L68 | N68: =SQRT(M68*G68^2+F68^2*K68^2) | O68: =Assumptions!$C$12 | P68: =O68*N68 | Q68: =F68*M68+P68 | S68: FALSE | T68: =IF(AND(S68,ISNUMBER(R68)),IF(R68>Q68,R68,Q68),Q68) | U68: =T68-F68*M68 | V68: 87.965812 | W68: =IF(ABS(T68-V68)<0.01,"OK","CHECK")
A69: SYN_HOBBIES_2_001_CA_2 | B69: SYN_HOBBIES_2_001 | C69: CA_2 | D69: HOBBIES | E69: erratic | F69: 4.2628775 | G69: 4.2893068 | H69: 14 | I69: 4 | J69: =MAX(H69+Assumptions!$C$7,1) | K69: =I69*Assumptions!$C$8 | L69: =Assumptions!$C$6 | M69: =J69+L69 | N69: =SQRT(M69*G69^2+F69^2*K69^2) | O69: =Assumptions!$C$12 | P69: =O69*N69 | Q69: =F69*M69+P69 | S69: FALSE | T69: =IF(AND(S69,ISNUMBER(R69)),IF(R69>Q69,R69,Q69),Q69) | U69: =T69-F69*M69 | V69: 132.32188 | W69: =IF(ABS(T69-V69)<0.01,"OK","CHECK")
A70: SYN_HOBBIES_2_004_CA_2 | B70: SYN_HOBBIES_2_004 | C70: CA_2 | D70: HOBBIES | E70: smooth | F70: 15.462898 | G70: 4.6490681 | H70: 14 | I70: 4 | J70: =MAX(H70+Assumptions!$C$7,1) | K70: =I70*Assumptions!$C$8 | L70: =Assumptions!$C$6 | M70: =J70+L70 | N70: =SQRT(M70*G70^2+F70^2*K70^2) | O70: =Assumptions!$C$12 | P70: =O70*N70 | Q70: =F70*M70+P70 | S70: FALSE | T70: =IF(AND(S70,ISNUMBER(R70)),IF(R70>Q70,R70,Q70),Q70) | U70: =T70-F70*M70 | V70: 432.32382 | W70: =IF(ABS(T70-V70)<0.01,"OK","CHECK")
A71: SYN_HOBBIES_2_006_CA_2 | B71: SYN_HOBBIES_2_006 | C71: CA_2 | D71: HOBBIES | E71: smooth | F71: 10.839361 | G71: 3.5103096 | H71: 14 | I71: 4 | J71: =MAX(H71+Assumptions!$C$7,1) | K71: =I71*Assumptions!$C$8 | L71: =Assumptions!$C$6 | M71: =J71+L71 | N71: =SQRT(M71*G71^2+F71^2*K71^2) | O71: =Assumptions!$C$12 | P71: =O71*N71 | Q71: =F71*M71+P71 | S71: FALSE | T71: =IF(AND(S71,ISNUMBER(R71)),IF(R71>Q71,R71,Q71),Q71) | U71: =T71-F71*M71 | V71: 303.69348 | W71: =IF(ABS(T71-V71)<0.01,"OK","CHECK")
A72: SYN_HOBBIES_2_009_CA_2 | B72: SYN_HOBBIES_2_009 | C72: CA_2 | D72: HOBBIES | E72: smooth | F72: 25.983545 | G72: 6.1185188 | H72: 14 | I72: 4 | J72: =MAX(H72+Assumptions!$C$7,1) | K72: =I72*Assumptions!$C$8 | L72: =Assumptions!$C$6 | M72: =J72+L72 | N72: =SQRT(M72*G72^2+F72^2*K72^2) | O72: =Assumptions!$C$12 | P72: =O72*N72 | Q72: =F72*M72+P72 | S72: FALSE | T72: =IF(AND(S72,ISNUMBER(R72)),IF(R72>Q72,R72,Q72),Q72) | U72: =T72-F72*M72 | V72: 722.72257 | W72: =IF(ABS(T72-V72)<0.01,"OK","CHECK")
A73: SYN_HOUSEHOLD_1_002_CA_2 | B73: SYN_HOUSEHOLD_1_002 | C73: CA_2 | D73: HOUSEHOLD | E73: smooth | F73: 22.930326 | G73: 6.1684842 | H73: 7 | I73: 2 | J73: =MAX(H73+Assumptions!$C$7,1) | K73: =I73*Assumptions!$C$8 | L73: =Assumptions!$C$6 | M73: =J73+L73 | N73: =SQRT(M73*G73^2+F73^2*K73^2) | O73: =Assumptions!$C$12 | P73: =O73*N73 | Q73: =F73*M73+P73 | S73: FALSE | T73: =IF(AND(S73,ISNUMBER(R73)),IF(R73>Q73,R73,Q73),Q73) | U73: =T73-F73*M73 | V73: 405.47305 | W73: =IF(ABS(T73-V73)<0.01,"OK","CHECK")
A74: SYN_HOUSEHOLD_1_004_CA_2 | B74: SYN_HOUSEHOLD_1_004 | C74: CA_2 | D74: HOUSEHOLD | E74: intermittent | F74: 1.3035714 | G74: 1.4184687 | H74: 7 | I74: 2 | J74: =MAX(H74+Assumptions!$C$7,1) | K74: =I74*Assumptions!$C$8 | L74: =Assumptions!$C$6 | M74: =J74+L74 | N74: =SQRT(M74*G74^2+F74^2*K74^2) | O74: =Assumptions!$C$12 | P74: =O74*N74 | Q74: =F74*M74+P74 | R74: 29 | S74: TRUE | T74: =IF(AND(S74,ISNUMBER(R74)),IF(R74>Q74,R74,Q74),Q74) | U74: =T74-F74*M74 | V74: 29 | W74: =IF(ABS(T74-V74)<0.01,"OK","CHECK")
A75: SYN_HOUSEHOLD_1_006_CA_2 | B75: SYN_HOUSEHOLD_1_006 | C75: CA_2 | D75: HOUSEHOLD | E75: intermittent | F75: 0.22375275 | G75: 0.58150383 | H75: 7 | I75: 2 | J75: =MAX(H75+Assumptions!$C$7,1) | K75: =I75*Assumptions!$C$8 | L75: =Assumptions!$C$6 | M75: =J75+L75 | N75: =SQRT(M75*G75^2+F75^2*K75^2) | O75: =Assumptions!$C$12 | P75: =O75*N75 | Q75: =F75*M75+P75 | R75: 7 | S75: TRUE | T75: =IF(AND(S75,ISNUMBER(R75)),IF(R75>Q75,R75,Q75),Q75) | U75: =T75-F75*M75 | V75: 7 | W75: =IF(ABS(T75-V75)<0.01,"OK","CHECK")
A76: SYN_HOUSEHOLD_1_008_CA_2 | B76: SYN_HOUSEHOLD_1_008 | C76: CA_2 | D76: HOUSEHOLD | E76: smooth | F76: 14.525147 | G76: 4.7624779 | H76: 7 | I76: 2 | J76: =MAX(H76+Assumptions!$C$7,1) | K76: =I76*Assumptions!$C$8 | L76: =Assumptions!$C$6 | M76: =J76+L76 | N76: =SQRT(M76*G76^2+F76^2*K76^2) | O76: =Assumptions!$C$12 | P76: =O76*N76 | Q76: =F76*M76+P76 | S76: FALSE | T76: =IF(AND(S76,ISNUMBER(R76)),IF(R76>Q76,R76,Q76),Q76) | U76: =T76-F76*M76 | V76: 259.4089 | W76: =IF(ABS(T76-V76)<0.01,"OK","CHECK")
A77: SYN_HOUSEHOLD_1_009_CA_2 | B77: SYN_HOUSEHOLD_1_009 | C77: CA_2 | D77: HOUSEHOLD | E77: smooth | F77: 11.053571 | G77: 4.2416409 | H77: 7 | I77: 2 | J77: =MAX(H77+Assumptions!$C$7,1) | K77: =I77*Assumptions!$C$8 | L77: =Assumptions!$C$6 | M77: =J77+L77 | N77: =SQRT(M77*G77^2+F77^2*K77^2) | O77: =Assumptions!$C$12 | P77: =O77*N77 | Q77: =F77*M77+P77 | S77: FALSE | T77: =IF(AND(S77,ISNUMBER(R77)),IF(R77>Q77,R77,Q77),Q77) | U77: =T77-F77*M77 | V77: 199.5132 | W77: =IF(ABS(T77-V77)<0.01,"OK","CHECK")
A78: SYN_HOUSEHOLD_2_001_CA_2 | B78: SYN_HOUSEHOLD_2_001 | C78: CA_2 | D78: HOUSEHOLD | E78: smooth | F78: 13.053571 | G78: 4.2391518 | H78: 10 | I78: 3.5 | J78: =MAX(H78+Assumptions!$C$7,1) | K78: =I78*Assumptions!$C$8 | L78: =Assumptions!$C$6 | M78: =J78+L78 | N78: =SQRT(M78*G78^2+F78^2*K78^2) | O78: =Assumptions!$C$12 | P78: =O78*N78 | Q78: =F78*M78+P78 | S78: FALSE | T78: =IF(AND(S78,ISNUMBER(R78)),IF(R78>Q78,R78,Q78),Q78) | U78: =T78-F78*M78 | V78: 302.37154 | W78: =IF(ABS(T78-V78)<0.01,"OK","CHECK")
A79: SYN_HOUSEHOLD_2_002_CA_2 | B79: SYN_HOUSEHOLD_2_002 | C79: CA_2 | D79: HOUSEHOLD | E79: intermittent | F79: 0.57142857 | G79: 1.1862305 | H79: 10 | I79: 3.5 | J79: =MAX(H79+Assumptions!$C$7,1) | K79: =I79*Assumptions!$C$8 | L79: =Assumptions!$C$6 | M79: =J79+L79 | N79: =SQRT(M79*G79^2+F79^2*K79^2) | O79: =Assumptions!$C$12 | P79: =O79*N79 | Q79: =F79*M79+P79 | R79: 12 | S79: TRUE | T79: =IF(AND(S79,ISNUMBER(R79)),IF(R79>Q79,R79,Q79),Q79) | U79: =T79-F79*M79 | V79: 18.405813 | W79: =IF(ABS(T79-V79)<0.01,"OK","CHECK")
A80: SYN_HOUSEHOLD_2_003_CA_2 | B80: SYN_HOUSEHOLD_2_003 | C80: CA_2 | D80: HOUSEHOLD | E80: erratic | F80: 3.8050575 | G80: 3.8552333 | H80: 10 | I80: 3.5 | J80: =MAX(H80+Assumptions!$C$7,1) | K80: =I80*Assumptions!$C$8 | L80: =Assumptions!$C$6 | M80: =J80+L80 | N80: =SQRT(M80*G80^2+F80^2*K80^2) | O80: =Assumptions!$C$12 | P80: =O80*N80 | Q80: =F80*M80+P80 | S80: FALSE | T80: =IF(AND(S80,ISNUMBER(R80)),IF(R80>Q80,R80,Q80),Q80) | U80: =T80-F80*M80 | V80: 98.795546 | W80: =IF(ABS(T80-V80)<0.01,"OK","CHECK")
A81: SYN_HOUSEHOLD_2_004_CA_2 | B81: SYN_HOUSEHOLD_2_004 | C81: CA_2 | D81: HOUSEHOLD | E81: smooth | F81: 22.553571 | G81: 6.1552823 | H81: 10 | I81: 3.5 | J81: =MAX(H81+Assumptions!$C$7,1) | K81: =I81*Assumptions!$C$8 | L81: =Assumptions!$C$6 | M81: =J81+L81 | N81: =SQRT(M81*G81^2+F81^2*K81^2) | O81: =Assumptions!$C$12 | P81: =O81*N81 | Q81: =F81*M81+P81 | S81: FALSE | T81: =IF(AND(S81,ISNUMBER(R81)),IF(R81>Q81,R81,Q81),Q81) | U81: =T81-F81*M81 | V81: 519.79692 | W81: =IF(ABS(T81-V81)<0.01,"OK","CHECK")
A82: SYN_HOUSEHOLD_2_005_CA_2 | B82: SYN_HOUSEHOLD_2_005 | C82: CA_2 | D82: HOUSEHOLD | E82: intermittent | F82: 0.94642857 | G82: 1.1484795 | H82: 10 | I82: 3.5 | J82: =MAX(H82+Assumptions!$C$7,1) | K82: =I82*Assumptions!$C$8 | L82: =Assumptions!$C$6 | M82: =J82+L82 | N82: =SQRT(M82*G82^2+F82^2*K82^2) | O82: =Assumptions!$C$12 | P82: =O82*N82 | Q82: =F82*M82+P82 | R82: 22 | S82: TRUE | T82: =IF(AND(S82,ISNUMBER(R82)),IF(R82>Q82,R82,Q82),Q82) | U82: =T82-F82*M82 | V82: 25.594739 | W82: =IF(ABS(T82-V82)<0.01,"OK","CHECK")
A83: SYN_HOUSEHOLD_2_006_CA_2 | B83: SYN_HOUSEHOLD_2_006 | C83: CA_2 | D83: HOUSEHOLD | E83: erratic | F83: 7.4203172 | G83: 6.8570382 | H83: 10 | I83: 3.5 | J83: =MAX(H83+Assumptions!$C$7,1) | K83: =I83*Assumptions!$C$8 | L83: =Assumptions!$C$6 | M83: =J83+L83 | N83: =SQRT(M83*G83^2+F83^2*K83^2) | O83: =Assumptions!$C$12 | P83: =O83*N83 | Q83: =F83*M83+P83 | S83: FALSE | T83: =IF(AND(S83,ISNUMBER(R83)),IF(R83>Q83,R83,Q83),Q83) | U83: =T83-F83*M83 | V83: 189.29194 | W83: =IF(ABS(T83-V83)<0.01,"OK","CHECK")
A84: SYN_HOUSEHOLD_2_008_CA_2 | B84: SYN_HOUSEHOLD_2_008 | C84: CA_2 | D84: HOUSEHOLD | E84: erratic | F84: 3.7699695 | G84: 3.0720289 | H84: 10 | I84: 3.5 | J84: =MAX(H84+Assumptions!$C$7,1) | K84: =I84*Assumptions!$C$8 | L84: =Assumptions!$C$6 | M84: =J84+L84 | N84: =SQRT(M84*G84^2+F84^2*K84^2) | O84: =Assumptions!$C$12 | P84: =O84*N84 | Q84: =F84*M84+P84 | S84: FALSE | T84: =IF(AND(S84,ISNUMBER(R84)),IF(R84>Q84,R84,Q84),Q84) | U84: =T84-F84*M84 | V84: 94.174585 | W84: =IF(ABS(T84-V84)<0.01,"OK","CHECK")

Sheet Reorder Points
A1: Reorder points, order-up-to levels and order quantities (MODELED)
A2: Live formulas referencing the Safety Stock sheet. On-hand and on-order stock are SIMULATED.
A4: Series | B4: Item | C4: Store | D4: mu | E4: Reorder point s | F4: Unit cost | G4: Order cost | H4: Holding $/unit/yr | I4: EOQ | J4: Cycle stock | K4: Order-up-to S | L4: On hand | M4: On order | N4: Inventory position | O4: Order needed? | P4: Raw need | Q4: Case pack | R4: MOQ (units) | S4: Recommended qty | T4: Coverage (days) | U4: Python qty | V4: Check vs Python
A5: SYN_FOODS_1_001_CA_1 | B5: SYN_FOODS_1_001 | C5: CA_1 | D5: ='Safety Stock'!F5 | E5: ='Safety Stock'!T5 | F5: 3.77 | G5: 6 | H5: =F5*Assumptions!$C$9 | I5: =IF(AND(D5>0,H5>0),SQRT(2*365*D5*G5/H5),0) | J5: =MIN(MAX(I5,D5*Assumptions!$C$6),D5*Assumptions!$C$11) | K5: =E5+J5 | L5: 75 | M5: 0 | N5: =L5+M5 | O5: =AND(N5<=E5+0.000000001,K5-N5>0.000000001) | P5: =IF(O5,K5-N5,0) | Q5: 12 | R5: 12 | S5: =IF(O5,MAX(CEILING(ROUND(P5/Q5,6),1)*Q5,CEILING(R5/Q5,1)*Q5),0) | T5: =IF(D5>0,L5/D5,"no demand") | U5: 132 | V5: =IF(S5=U5,"OK","CHECK")
A6: SYN_FOODS_1_003_CA_1 | B6: SYN_FOODS_1_003 | C6: CA_1 | D6: ='Safety Stock'!F6 | E6: ='Safety Stock'!T6 | F6: 1.88 | G6: 6 | H6: =F6*Assumptions!$C$9 | I6: =IF(AND(D6>0,H6>0),SQRT(2*365*D6*G6/H6),0) | J6: =MIN(MAX(I6,D6*Assumptions!$C$6),D6*Assumptions!$C$11) | K6: =E6+J6 | L6: 28 | M6: 0 | N6: =L6+M6 | O6: =AND(N6<=E6+0.000000001,K6-N6>0.000000001) | P6: =IF(O6,K6-N6,0) | Q6: 2 | R6: 2 | S6: =IF(O6,MAX(CEILING(ROUND(P6/Q6,6),1)*Q6,CEILING(R6/Q6,1)*Q6),0) | T6: =IF(D6>0,L6/D6,"no demand") | U6: 0 | V6: =IF(S6=U6,"OK","CHECK")
A7: SYN_FOODS_1_008_CA_1 | B7: SYN_FOODS_1_008 | C7: CA_1 | D7: ='Safety Stock'!F7 | E7: ='Safety Stock'!T7 | F7: 4.63 | G7: 6 | H7: =F7*Assumptions!$C$9 | I7: =IF(AND(D7>0,H7>0),SQRT(2*365*D7*G7/H7),0) | J7: =MIN(MAX(I7,D7*Assumptions!$C$6),D7*Assumptions!$C$11) | K7: =E7+J7 | L7: 30 | M7: 0 | N7: =L7+M7 | O7: =AND(N7<=E7+0.000000001,K7-N7>0.000000001) | P7: =IF(O7,K7-N7,0) | Q7: 6 | R7: 6 | S7: =IF(O7,MAX(CEILING(ROUND(P7/Q7,6),1)*Q7,CEILING(R7/Q7,1)*Q7),0) | T7: =IF(D7>0,L7/D7,"no demand") | U7: 84 | V7: =IF(S7=U7,"OK","CHECK")
A8: SYN_FOODS_1_009_CA_1 | B8: SYN_FOODS_1_009 | C8: CA_1 | D8: ='Safety Stock'!F8 | E8: ='Safety Stock'!T8 | F8: 5.45 | G8: 6 | H8: =F8*Assumptions!$C$9 | I8: =IF(AND(D8>0,H8>0),SQRT(2*365*D8*G8/H8),0) | J8: =MIN(MAX(I8,D8*Assumptions!$C$6),D8*Assumptions!$C$11) | K8: =E8+J8 | L8: 318 | M8: 0 | N8: =L8+M8 | O8: =AND(N8<=E8+0.000000001,K8-N8>0.000000001) | P8: =IF(O8,K8-N8,0) | Q8: 12 | R8: 12 | S8: =IF(O8,MAX(CEILING(ROUND(P8/Q8,6),1)*Q8,CEILING(R8/Q8,1)*Q8),0) | T8: =IF(D8>0,L8/D8,"no demand") | U8: 0 | V8: =IF(S8=U8,"OK","CHECK")
A9: SYN_FOODS_2_004_CA_1 | B9: SYN_FOODS_2_004 | C9: CA_1 | D9: ='Safety Stock'!F9 | E9: ='Safety Stock'!T9 | F9: 2.01 | G9: 6 | H9: =F9*Assumptions!$C$9 | I9: =IF(AND(D9>0,H9>0),SQRT(2*365*D9*G9/H9),0) | J9: =MIN(MAX(I9,D9*Assumptions!$C$6),D9*Assumptions!$C$11) | K9: =E9+J9 | L9: 15 | M9: 0 | N9: =L9+M9 | O9: =AND(N9<=E9+0.000000001,K9-N9>0.000000001) | P9: =IF(O9,K9-N9,0) | Q9: 2 | R9: 2 | S9: =IF(O9,MAX(CEILING(ROUND(P9/Q9,6),1)*Q9,CEILING(R9/Q9,1)*Q9),0) | T9: =IF(D9>0,L9/D9,"no demand") | U9: 34 | V9: =IF(S9=U9,"OK","CHECK")
A10: SYN_FOODS_2_005_CA_1 | B10: SYN_FOODS_2_005 | C10: CA_1 | D10: ='Safety Stock'!F10 | E10: ='Safety Stock'!T10 | F10: 5.21 | G10: 6 | H10: =F10*Assumptions!$C$9 | I10: =IF(AND(D10>0,H10>0),SQRT(2*365*D10*G10/H10),0) | J10: =MIN(MAX(I10,D10*Assumptions!$C$6),D10*Assumptions!$C$11) | K10: =E10+J10 | L10: 12 | M10: 0 | N10: =L10+M10 | O10: =AND(N10<=E10+0.000000001,K10-N10>0.000000001) | P10: =IF(O10,K10-N10,0) | Q10: 4 | R10: 4 | S10: =IF(O10,MAX(CEILING(ROUND(P10/Q10,6),1)*Q10,CEILING(R10/Q10,1)*Q10),0) | T10: =IF(D10>0,L10/D10,"no demand") | U10: 80 | V10: =IF(S10=U10,"OK","CHECK")
A11: SYN_FOODS_2_006_CA_1 | B11: SYN_FOODS_2_006 | C11: CA_1 | D11: ='Safety Stock'!F11 | E11: ='Safety Stock'!T11 | F11: 1.46 | G11: 6 | H11: =F11*Assumptions!$C$9 | I11: =IF(AND(D11>0,H11>0),SQRT(2*365*D11*G11/H11),0) | J11: =MIN(MAX(I11,D11*Assumptions!$C$6),D11*Assumptions!$C$11) | K11: =E11+J11 | L11: 66 | M11: 0 | N11: =L11+M11 | O11: =AND(N11<=E11+0.000000001,K11-N11>0.000000001) | P11: =IF(O11,K11-N11,0) | Q11: 6 | R11: 6 | S11: =IF(O11,MAX(CEILING(ROUND(P11/Q11,6),1)*Q11,CEILING(R11/Q11,1)*Q11),0) | T11: =IF(D11>0,L11/D11,"no demand") | U11: 0 | V11: =IF(S11=U11,"OK","CHECK")
A12: SYN_FOODS_2_008_CA_1 | B12: SYN_FOODS_2_008 | C12: CA_1 | D12: ='Safety Stock'!F12 | E12: ='Safety Stock'!T12 | F12: 4.95 | G12: 6 | H12: =F12*Assumptions!$C$9 | I12: =IF(AND(D12>0,H12>0),SQRT(2*365*D12*G12/H12),0) | J12: =MIN(MAX(I12,D12*Assumptions!$C$6),D12*Assumptions!$C$11) | K12: =E12+J12 | L12: 7 | M12: 0 | N12: =L12+M12 | O12: =AND(N12<=E12+0.000000001,K12-N12>0.000000001) | P12: =IF(O12,K12-N12,0) | Q12: 4 | R12: 4 | S12: =IF(O12,MAX(CEILING(ROUND(P12/Q12,6),1)*Q12,CEILING(R12/Q12,1)*Q12),0) | T12: =IF(D12>0,L12/D12,"no demand") | U12: 36 | V12: =IF(S12=U12,"OK","CHECK")
A13: SYN_FOODS_2_009_CA_1 | B13: SYN_FOODS_2_009 | C13: CA_1 | D13: ='Safety Stock'!F13 | E13: ='Safety Stock'!T13 | F13: 4.18 | G13: 6 | H13: =F13*Assumptions!$C$9 | I13: =IF(AND(D13>0,H13>0),SQRT(2*365*D13*G13/H13),0) | J13: =MIN(MAX(I13,D13*Assumptions!$C$6),D13*Assumptions!$C$11) | K13: =E13+J13 | L13: 583 | M13: 0 | N13: =L13+M13 | O13: =AND(N13<=E13+0.000000001,K13-N13>0.000000001) | P13: =IF(O13,K13-N13,0) | Q13: 12 | R13: 12 | S13: =IF(O13,MAX(CEILING(ROUND(P13/Q13,6),1)*Q13,CEILING(R13/Q13,1)*Q13),0) | T13: =IF(D13>0,L13/D13,"no demand") | U13: 0 | V13: =IF(S13=U13,"OK","CHECK")
A14: SYN_FOODS_3_002_CA_1 | B14: SYN_FOODS_3_002 | C14: CA_1 | D14: ='Safety Stock'!F14 | E14: ='Safety Stock'!T14 | F14: 2.42 | G14: 4 | H14: =F14*Assumptions!$C$9 | I14: =IF(AND(D14>0,H14>0),SQRT(2*365*D14*G14/H14),0) | J14: =MIN(MAX(I14,D14*Assumptions!$C$6),D14*Assumptions!$C$11) | K14: =E14+J14 | L14: 61 | M14: 0 | N14: =L14+M14 | O14: =AND(N14<=E14+0.000000001,K14-N14>0.000000001) | P14: =IF(O14,K14-N14,0) | Q14: 6 | R14: 6 | S14: =IF(O14,MAX(CEILING(ROUND(P14/Q14,6),1)*Q14,CEILING(R14/Q14,1)*Q14),0) | T14: =IF(D14>0,L14/D14,"no demand") | U14: 0 | V14: =IF(S14=U14,"OK","CHECK")
A15: SYN_FOODS_3_003_CA_1 | B15: SYN_FOODS_3_003 | C15: CA_1 | D15: ='Safety Stock'!F15 | E15: ='Safety Stock'!T15 | F15: 1.27 | G15: 4 | H15: =F15*Assumptions!$C$9 | I15: =IF(AND(D15>0,H15>0),SQRT(2*365*D15*G15/H15),0) | J15: =MIN(MAX(I15,D15*Assumptions!$C$6),D15*Assumptions!$C$11) | K15: =E15+J15 | L15: 284 | M15: 0 | N15: =L15+M15 | O15: =AND(N15<=E15+0.000000001,K15-N15>0.000000001) | P15: =IF(O15,K15-N15,0) | Q15: 12 | R15: 12 | S15: =IF(O15,MAX(CEILING(ROUND(P15/Q15,6),1)*Q15,CEILING(R15/Q15,1)*Q15),0) | T15: =IF(D15>0,L15/D15,"no demand") | U15: 0 | V15: =IF(S15=U15,"OK","CHECK")
A16: SYN_FOODS_3_004_CA_1 | B16: SYN_FOODS_3_004 | C16: CA_1 | D16: ='Safety Stock'!F16 | E16: ='Safety Stock'!T16 | F16: 0.96 | G16: 4 | H16: =F16*Assumptions!$C$9 | I16: =IF(AND(D16>0,H16>0),SQRT(2*365*D16*G16/H16),0) | J16: =MIN(MAX(I16,D16*Assumptions!$C$6),D16*Assumptions!$C$11) | K16: =E16+J16 | L16: 276 | M16: 0 | N16: =L16+M16 | O16: =AND(N16<=E16+0.000000001,K16-N16>0.000000001) | P16: =IF(O16,K16-N16,0) | Q16: 12 | R16: 12 | S16: =IF(O16,MAX(CEILING(ROUND(P16/Q16,6),1)*Q16,CEILING(R16/Q16,1)*Q16),0) | T16: =IF(D16>0,L16/D16,"no demand") | U16: 0 | V16: =IF(S16=U16,"OK","CHECK")
... A84: SYN_HOUSEHOLD_2_008_CA_2 | B84: SYN_HOUSEHOLD_2_008 | C84: CA_2 | D84: ='Safety Stock'!F84 | E84: ='Safety Stock'!T84 | F84: 2.62 | G84: 8 | H84: =F84*Assumptions!$C$9 | I84: =IF(AND(D84>0,H84>0),SQRT(2*365*D84*G84/H84),0) | J84: =MIN(MAX(I84,D84*Assumptions!$C$6),D84*Assumptions!$C$11) | K84: =E84+J84 | L84: 14 | M84: 120 | N84: =L84+M84 | O84: =AND(N84<=E84+0.000000001,K84-N84>0.000000001) | P84: =IF(O84,K84-N84,0) | Q84: 12 | R84: 12 | S84: =IF(O84,MAX(CEILING(ROUND(P84/Q84,6),1)*Q84,CEILING(R84/Q84,1)*Q84),0) | T84: =IF(D84>0,L84/D84,"no demand") | U84: 0 | V84: =IF(S84=U84,"OK","CHECK")

Sheet Purchase Recs
A1: Purchase recommendations
A2: Recommended qty is live (Reorder Points). Funded qty applies supplier capacity and budget in priority order (Python allocation, values).
A4: Series | B4: Item | C4: Store | D4: Supplier | E4: Risk | F4: Priority | G4: Recommended qty (live) | H4: Funded qty (Python) | I4: Status | J4: Unit cost | K4: Order value | L4: Expected receipt | M4: Reason
A5: SYN_FOODS_1_001_CA_1 | B5: SYN_FOODS_1_001 | C5: CA_1 | D5: SUP-01 | E5: Medium | F5: 32 | G5: ='Reorder Points'!S5 | H5: 132 | I5: Order | J5: 3.77 | K5: =H5*J5 | L5: 2026-05-02 | M5: Inventory position 75 is at or below the reorder point 75.8. Ordering up to 199.3 needs 124.3 units, rounded up to whole cases of 12 = 132 units.
A6: SYN_FOODS_1_003_CA_1 | B6: SYN_FOODS_1_003 | C6: CA_1 | D6: SUP-01 | E6: Low | F6: 79 | G6: ='Reorder Points'!S6 | H6: 0 | I6: No order needed | J6: 1.88 | K6: =H6*J6 | L6: nan | M6: Inventory position 28 is above the reorder point 17.0; no order is needed at this review.
A7: SYN_FOODS_1_008_CA_1 | B7: SYN_FOODS_1_008 | C7: CA_1 | D7: SUP-01 | E7: Medium | F7: 24 | G7: ='Reorder Points'!S7 | H7: 84 | I7: Order | J7: 4.63 | K7: =H7*J7 | L7: 2026-05-02 | M7: Inventory position 30 is at or below the reorder point 45.0. Ordering up to 111.4 needs 81.4 units, rounded up to whole cases of 6 = 84 units.
A8: SYN_FOODS_1_009_CA_1 | B8: SYN_FOODS_1_009 | C8: CA_1 | D8: SUP-01 | E8: Low | F8: 63 | G8: ='Reorder Points'!S8 | H8: 0 | I8: No order needed | J8: 5.45 | K8: =H8*J8 | L8: nan | M8: Inventory position 318 is above the reorder point 198.0; no order is needed at this review.
A9: SYN_FOODS_2_004_CA_1 | B9: SYN_FOODS_2_004 | C9: CA_1 | D9: SUP-02 | E9: Medium | F9: 22 | G9: ='Reorder Points'!S9 | H9: 34 | I9: Order | J9: 2.01 | K9: =H9*J9 | L9: 2026-05-03 | M9: Inventory position 15 is at or below the reorder point 20.5. Ordering up to 47.8 needs 32.8 units, rounded up to whole cases of 2 = 34 units.
A10: SYN_FOODS_2_005_CA_1 | B10: SYN_FOODS_2_005 | C10: CA_1 | D10: SUP-02 | E10: Medium | F10: 8 | G10: ='Reorder Points'!S10 | H10: 80 | I10: Order | J10: 5.21 | K10: =H10*J10 | L10: 2026-05-03 | M10: Inventory position 12 is at or below the reorder point 48.0. Ordering up to 90.0 needs 78.0 units, rounded up to whole cases of 4 = 80 units.
A11: SYN_FOODS_2_006_CA_1 | B11: SYN_FOODS_2_006 | C11: CA_1 | D11: SUP-02 | E11: Low | F11: 75 | G11: ='Reorder Points'!S11 | H11: 0 | I11: No order needed | J11: 1.46 | K11: =H11*J11 | L11: nan | M11: Inventory position 66 is above the reorder point 34.2; no order is needed at this review.
A12: SYN_FOODS_2_008_CA_1 | B12: SYN_FOODS_2_008 | C12: CA_1 | D12: SUP-02 | E12: Medium | F12: 10 | G12: ='Reorder Points'!S12 | H12: 36 | I12: Order | J12: 4.95 | K12: =H12*J12 | L12: 2026-05-03 | M12: Inventory position 7 is at or below the reorder point 17.0. Ordering up to 39.6 needs 32.6 units, rounded up to whole cases of 4 = 36 units.
A13: SYN_FOODS_2_009_CA_1 | B13: SYN_FOODS_2_009 | C13: CA_1 | D13: SUP-02 | E13: Low | F13: 59 | G13: ='Reorder Points'!S13 | H13: 0 | I13: No order needed | J13: 4.18 | K13: =H13*J13 | L13: nan | M13: Inventory position 583 is above the reorder point 459.4; no order is needed at this review.
A14: SYN_FOODS_3_002_CA_1 | B14: SYN_FOODS_3_002 | C14: CA_1 | D14: SUP-03 | E14: Low | F14: 74 | G14: ='Reorder Points'!S14 | H14: 0 | I14: No order needed | J14: 2.42 | K14: =H14*J14 | L14: nan | M14: Inventory position 61 is above the reorder point 32.6; no order is needed at this review.
A15: SYN_FOODS_3_003_CA_1 | B15: SYN_FOODS_3_003 | C15: CA_1 | D15: SUP-03 | E15: Low | F15: 69 | G15: ='Reorder Points'!S15 | H15: 0 | I15: No order needed | J15: 1.27 | K15: =H15*J15 | L15: nan | M15: Inventory position 284 is above the reorder point 139.6; no order is needed at this review.
A16: SYN_FOODS_3_004_CA_1 | B16: SYN_FOODS_3_004 | C16: CA_1 | D16: SUP-03 | E16: Low | F16: 71 | G16: ='Reorder Points'!S16 | H16: 0 | I16: No order needed | J16: 0.96 | K16: =H16*J16 | L16: nan | M16: Inventory position 276 is above the reorder point 143.9; no order is needed at this review.
... A84: SYN_HOUSEHOLD_2_008_CA_2 | B84: SYN_HOUSEHOLD_2_008 | C84: CA_2 | D84: SUP-06 | E84: Low | F84: 54 | G84: ='Reorder Points'!S84 | H84: 0 | I84: No order needed | J84: 2.62 | K84: =H84*J84 | L84: nan | M84: Inventory position 134 is above the reorder point 94.2; no order is needed at this review.
J86: Total | K86: =SUM(K5:K84)
J87: Lines funded | K87: =COUNTIF(H5:H84,">0")
J88: Budget | K88: Unconstrained

Sheet Suppliers
A1: Supplier assumptions (SIMULATED)
A2: Fictional suppliers assigned by department. Capacity is units per 7-day review.
A4: Supplier | B4: Name | C4: Departments | D4: Base lead time (d) | E4: Base LT sd (d) | F4: Lead time used (d) | G4: LT sd used (d) | H4: MOQ (cases) | I4: Order cost / line | J4: Capacity (units/wk) | K4: On-time rate (assumed) | L4: Lines | M4: Recommended spend
A5: SUP-01 | B5: Dry Grocery Supplier (simulated) | C5: FOODS_1 | D5: 5 | E5: 1 | F5: =MAX(D5+Assumptions!$C$7,1) | G5: =E5*Assumptions!$C$8 | H5: 1 | I5: 6 | J5: 808 | K5: 0.93 | L5: =COUNTIF('Purchase Recs'!$D$5:$D$84,A5) | M5: =SUMIF('Purchase Recs'!$D$5:$D$84,A5,'Purchase Recs'!$K$5:$K$84)
A6: SUP-02 | B6: Packaged Foods Supplier (simulated) | C6: FOODS_2 | D6: 6 | E6: 1.5 | F6: =MAX(D6+Assumptions!$C$7,1) | G6: =E6*Assumptions!$C$8 | H6: 1 | I6: 6 | J6: 691 | K6: 0.9 | L6: =COUNTIF('Purchase Recs'!$D$5:$D$84,A6) | M6: =SUMIF('Purchase Recs'!$D$5:$D$84,A6,'Purchase Recs'!$K$5:$K$84)
A7: SUP-03 | B7: Regional Fresh & Staples DC (simulated) | C7: FOODS_3 | D7: 3 | E7: 0.8 | F7: =MAX(D7+Assumptions!$C$7,1) | G7: =E7*Assumptions!$C$8 | H7: 1 | I7: 4 | J7: 1314 | K7: 0.95 | L7: =COUNTIF('Purchase Recs'!$D$5:$D$84,A7) | M7: =SUMIF('Purchase Recs'!$D$5:$D$84,A7,'Purchase Recs'!$K$5:$K$84)
A8: SUP-04 | B8: Import Hobby Goods Supplier (simulated) | C8: HOBBIES_1, HOBBIES_2 | D8: 14 | E8: 4 | F8: =MAX(D8+Assumptions!$C$7,1) | G8: =E8*Assumptions!$C$8 | H8: 2 | I8: 9 | J8: 2155 | K8: 0.74 | L8: =COUNTIF('Purchase Recs'!$D$5:$D$84,A8) | M8: =SUMIF('Purchase Recs'!$D$5:$D$84,A8,'Purchase Recs'!$K$5:$K$84)
A9: SUP-05 | B9: Household Essentials Supplier (simulated) | C9: HOUSEHOLD_1 | D9: 7 | E9: 2 | F9: =MAX(D9+Assumptions!$C$7,1) | G9: =E9*Assumptions!$C$8 | H9: 1 | I9: 7 | J9: 834 | K9: 0.88 | L9: =COUNTIF('Purchase Recs'!$D$5:$D$84,A9) | M9: =SUMIF('Purchase Recs'!$D$5:$D$84,A9,'Purchase Recs'!$K$5:$K$84)
A10: SUP-06 | B10: Home Goods Supplier (simulated) | C10: HOUSEHOLD_2 | D10: 10 | E10: 3.5 | F10: =MAX(D10+Assumptions!$C$7,1) | G10: =E10*Assumptions!$C$8 | H10: 1 | I10: 8 | J10: 1156 | K10: 0.81 | L10: =COUNTIF('Purchase Recs'!$D$5:$D$84,A10) | M10: =SUMIF('Purchase Recs'!$D$5:$D$84,A10,'Purchase Recs'!$K$5:$K$84)

Sheet Scenarios
A1: Scenario and policy comparisons (Python engine, values)
A2: Scenarios recompute today's plan from the same immutable baseline. Simulation results are SIMULATED.
A4: Scenario | B4: Service level | C4: Review (d) | D4: LT shift (d) | E4: LT sd x | F4: Budget | G4: Lines ordering | H4: Lines deferred | I4: Purchase spend | J4: High-risk lines | K4: Exp. short (cycle) | L4: Annual holding | M4: Annual ordering | N4: Annual shortage | O4: Annual total
A5: balanced | B5: 0.95 | C5: 7 | D5: 0 | E5: 1 | F5: Unconstrained | G5: 33 | H5: 0 | I5: 22791.08 | J5: 6 | K5: 2.8191519 | L5: 11357.811 | M5: 9183.0303 | N5: 5158.0526 | O5: 25698.894
A6: protect | B6: 0.99 | C6: 7 | D6: 0 | E6: 1 | F6: Unconstrained | G6: 40 | H6: 4 | I6: 29129.98 | J6: 6 | K6: 3.2806579 | L6: 13291.685 | M6: 9183.0303 | N6: 834.63525 | O6: 23309.35
A7: limit | B7: 0.95 | C7: 7 | D7: 0 | E7: 1 | F7: 13674.65 | G7: 23 | H7: 10 | I7: 13674.36 | J7: 6 | K7: 61.509866 | L7: 11357.811 | M7: 9183.0303 | N7: 5158.0526 | O7: 25698.894
A8: lead_time_plus_5 | B8: 0.95 | C8: 7 | D8: 5 | E8: 1 | F8: Unconstrained | G8: 45 | H8: 6 | I8: 32987.62 | J8: 12 | K8: 41.076132 | L8: 11587.526 | M8: 9183.0303 | N8: 5333.6023 | O8: 26104.159
A9: variability_x2 | B9: 0.95 | C9: 7 | D9: 0 | E9: 2 | F9: Unconstrained | G9: 34 | H9: 7 | I9: 29606.4 | J9: 6 | K9: 33.387257 | L9: 14709.125 | M9: 9183.0303 | N9: 9366.9964 | O9: 33259.152
A10: review_14 | B10: 0.95 | C10: 14 | D10: 0 | E10: 1 | F10: Unconstrained | G10: 57 | H10: 0 | I10: 58305.82 | J10: 6 | K10: 3.5382463 | L10: 12132.23 | M10: 8838.7703 | N10: 4842.253 | O10: 25813.253
A11: zero_budget | B11: 0.95 | C11: 7 | D11: 0 | E11: 1 | F11: 0 | G11: 0 | H11: 33 | I11: 0 | J11: 6 | K11: 263.83171 | L11: 11357.811 | M11: 9183.0303 | N11: 5158.0526 | O11: 25698.894
A12: csl_80 | B12: 0.8 | C12: 7 | D12: 0 | E12: 1 | F12: Unconstrained | G12: 25 | H12: 0 | I12: 14725.16 | J12: 6 | K12: 12.818805 | L12: 9052.3686 | M12: 9183.0303 | N12: 27766.596 | O12: 46001.994
A15: Historical simulation: basic vs forecast-informed policies (SIMULATED, 182 days each window)
A16: Window | B16: Scope | C16: Policy | D16: Lines | E16: Fill rate | F16: Cycle service level | G16: Lost units | H16: Stockout days | I16: Avg inventory value | J16: POs | K16: Purchasing spend (not a cost) | L16: Holding cost | M16: Ordering cost | N16: Shortage penalty | O16: Modeled total cost
A17: main | B17: demo | C17: Basic min/max rule (status quo) | D17: 80 | E17: 0.99383488 | F17: 0.9680461 | G17: 695 | H17: 120 | I17: 65360.765 | J17: 675 | K17: 585152.84 | L17: 8147.71 | M17: 4712 | N17: 3676.89 | O17: 16536.6
A18: main | B18: demo | C18: Forecast policy v1 (pre-specified) | D18: 80 | E18: 0.99483727 | F18: 0.9848088 | G18: 582 | H18: 69 | I18: 67112.477 | J18: 445 | K18: 586474.82 | L18: 8366.08 | M18: 3117 | N18: 3127.52 | O18: 14610.59
A19: main | B19: demo | C19: Forecast policy v2 (28-day lot cap, revised after v1) | D19: 80 | E19: 0.99634528 | F19: 0.98742797 | G19: 412 | H19: 53 | I19: 64114.881 | J19: 536 | K19: 582768.52 | L19: 7992.4 | M19: 3751 | N19: 2624.45 | O19: 14367.85
A20: main | B20: model_stores | C20: Basic min/max rule (status quo) | D20: 126 | E20: 0.99456165 | F20: 0.96558704 | G20: 804 | H20: 181 | I20: 79007.781 | J20: 1020 | K20: 700107.88 | L20: 9848.92 | M20: 7034 | N20: 4181.01 | O20: 21063.93
A21: main | B21: model_stores | C21: Forecast policy v1 (pre-specified) | D21: 126 | E21: 0.99326294 | F21: 0.97975709 | G21: 996 | H21: 149 | I21: 86531.884 | J21: 615 | K21: 710440.76 | L21: 10786.85 | M21: 4253 | N21: 4414.32 | O21: 19454.17
A22: main | B22: model_stores | C22: Forecast policy v2 (28-day lot cap, revised after v1) | D22: 126 | E22: 0.99524483 | F22: 0.98380567 | G22: 703 | H22: 118 | I22: 80702.447 | J22: 778 | K22: 704458.68 | L22: 10060.17 | M22: 5384 | N22: 3963.45 | O22: 19407.62
A23: confirmation | B23: demo | C23: Basic min/max rule (status quo) | D23: 80 | E23: 0.99591737 | F23: 0.9640592 | G23: 450 | H23: 131 | I23: 62668.759 | J23: 685 | K23: 573423.72 | L23: 7812.13 | M23: 4811 | N23: 2223.76 | O23: 14846.9
A24: confirmation | B24: demo | C24: Forecast policy v1 (pre-specified) | D24: 80 | E24: 0.99750506 | F24: 0.98837209 | G24: 275 | H24: 42 | I24: 63803.398 | J24: 450 | K24: 574061.58 | L24: 7953.57 | M24: 3151 | N24: 1393.52 | O24: 12498.09
A25: confirmation | B25: demo | C25: Forecast policy v2 (28-day lot cap, revised after v1) | D25: 80 | E25: 0.99712401 | F25: 0.98678647 | G25: 317 | H25: 49 | I25: 61110.71 | J25: 546 | K25: 571573.22 | L25: 7617.91 | M25: 3825 | N25: 1716.72 | O25: 13159.63
A26: confirmation | B26: model_stores | C26: Basic min/max rule (status quo) | D26: 126 | E26: 0.99504236 | F26: 0.96016343 | G26: 721 | H26: 216 | I26: 75611.986 | J26: 1038 | K26: 690392.78 | L26: 9425.6 | M26: 7181 | N26: 3021.77 | O26: 19628.37
A27: confirmation | B27: model_stores | C27: Forecast policy v1 (pre-specified) | D27: 126 | E27: 0.99467105 | F27: 0.98195438 | G27: 775 | H27: 113 | I27: 82055.568 | J27: 611 | K27: 690982.5 | L27: 10228.84 | M27: 4198 | N27: 2875.55 | O27: 17302.39
A28: confirmation | B28: model_stores | C28: Forecast policy v2 (28-day lot cap, revised after v1) | D28: 126 | E28: 0.99733209 | F28: 0.98535921 | G28: 388 | H28: 71 | I28: 77259.974 | J28: 781 | K28: 691279.56 | L28: 9631.04 | M28: 5399 | N28: 1640.73 | O28: 16670.77
A47: Cost sensitivity (decisions held fixed; margin and shortage penalty varied)
A48: Margin shift | B48: Shortage multiplier | C48: Basic: total cost | D48: Forecast v1: total cost | E48: Forecast v2: total cost | F48: v2 - basic
A49: -0.1 | B49: 0.5 | C49: 15082.1 | D49: 13618.07 | E49: 13696.24 | F49: =E49-C49
A50: -0.1 | B50: 1 | C50: 15996.7 | D50: 14402.77 | E50: 14359.15 | F50: =E50-C50
A51: -0.1 | B51: 1.5 | C51: 16911.29 | D51: 15187.46 | E51: 15022.05 | F51: =E51-C51
A52: -0.1 | B52: 2 | C52: 17825.89 | D52: 15972.16 | E52: 15684.96 | F52: =E52-C52
A53: -0.1 | B53: 3 | C53: 19655.08 | D53: 17541.55 | E53: 17010.77 | F53: =E53-C53
A54: 0 | B54: 0.5 | C54: 14085.34 | D54: 12525.58 | E54: 12618.22 | F54: =E54-C54
A55: 0 | B55: 1 | C55: 15310.97 | D55: 13568.09 | E55: 13493.03 | F55: =E55-C55
A56: 0 | B56: 1.5 | C56: 16536.6 | D56: 14610.59 | E56: 14367.85 | F56: =E56-C56
A57: 0 | B57: 2 | C57: 17762.23 | D57: 15653.1 | E57: 15242.66 | F57: =E57-C57
A58: 0 | B58: 3 | C58: 20213.49 | D58: 17738.11 | E58: 16992.29 | F58: =E58-C58
A59: 0.1 | B59: 0.5 | C59: 13090.21 | D59: 11434.57 | E59: 11541.28 | F59: =E59-C59
A60: 0.1 | B60: 1 | C60: 14626.82 | D60: 12735.11 | E60: 12627.82 | F60: =E60-C60
... A63: 0.1 | B63: 3 | C63: 20773.24 | D63: 17937.29 | E63: 16973.96 | F63: =E63-C63

Sheet Data Definitions
A1: Data definitions and lineage
A2: OBSERVED = M5 records; DERIVED = computed from observed; MODELED = forecasts and plans; SIMULATED = assumptions.
A4: Field | B4: Definition | C4: Lineage
A5: Series | B5: Product-store combination (M5 item_id + store_id). | C5: OBSERVED
A6: mu | B6: Expected daily demand: mean of the selected model's 28-day forecast after the last observed day. | C6: MODELED
A7: sigma | B7: Std. deviation (RMSE) of daily forecast errors across five 28-day validation folds. | C7: MODELED
A8: Demand pattern | B8: Syntetos-Boylan class from average inter-demand interval (1.32) and squared CV of demand sizes (0.49). | C8: DERIVED
A9: ABC / XYZ | B9: ABC on cumulative 364-day sales value; XYZ on coefficient of variation of weekly demand. | C9: DERIVED
A10: Lead time, LT sd | B10: Supplier mean lead time and its standard deviation in days. | C10: SIMULATED
A11: Case pack, MOQ | B11: Units per case set from item velocity; MOQ = supplier minimum cases x case pack. | C11: SIMULATED
A12: Unit price | B12: Median weekly shelf price over the 364 days before the simulation start. | C12: OBSERVED/DERIVED
A13: Unit cost | B13: Unit price x (1 - assumed category gross margin). | C13: SIMULATED
A14: On hand / on order | B14: Ending state of the 182-day simulation of the basic policy at the planning date. | C14: SIMULATED
A15: Safety stock | B15: z x sigma_P (normal) or the empirical-quantile fallback for intermittent items. | C15: MODELED
... A23: Modeled total cost | B23: Holding + ordering + shortage penalty. Purchasing spend is reported separately and is not counted as a cost. | C23: SIMULATED
